{"metadata": {"dataVersion": "2", "matchId": "NA1_4353501561", "participants": ["7q4P678k91vcj4qQceUzO6PdTh7WImXg-ce_mn_jkBXoBBoTMTwrBulOKM1rcLMj4_5B28yAOX-tuw", "C0t14iPbMv-GcaamUzSFVKEyJNOiPIntPymyR84i8ZfsPH6PRZppSNxM9hYHrPpeauCSYpJiNWwZ0w", "lu42OafJKXsa8E6Y645gT0iupCsyswCRAoc_r4cI0WYWG2AH1mxDFS9vK9Qg6SZFkE5pOvknRvtl0g", "oCsRQGGyIsQojXmeuWwzBaOQ_kvQp-D4EQgsPpSLL2Ucwi18Mq8cJxCrtmhbQSwVtLjO-MGQUP6jZw", "Y9Ohd25EirbZYITMPCqOhlTta4hBy-fA9R_H1hPuia6LRTX_z0Z1Xnm_g-DQ2URSZ-E5-vcPQ-mhwg", "Up-FdUJb98DyyYRuA7H6i1nNMVNTtRDWz8kwhsHcf9VUFe-4uSBt6rA64oTSEooo-hWooGv8ji5kUg", "-Q4TP5e0LLcrhi7jCHtIIiS5M9MnD1qnGKiRGSZuhNEJK9IJv3RbdsDtqxe1Zy-A22QbfzU7BUFWsQ", "w6wUMei237Ivkq7P4Htm20lrdvcbXNOXQH8ed7MHQSDZDWrRizg9PKz6-zDJX522rTY-2t0LtJMhtg", "PkM6S0PcDtaQVrFsgaUDuh42GmoX4qnot03Q66V-_mFqqVDt029bCfe4pn77tf9FhOE067gl1n0-TA", "APH8IvnSSc-olpTnr70_FGt-lnmL6PjeIP6S242tuRb1Py86ngS7aBDT7JNxJ0bQ56WTw3x-QjEjFQ"]}, "info": {"gameCreation": 1656124185000, "gameDuration": 1583, "gameEndTimestamp": 1656125812720, "gameId": 4353501561, "gameMode": "CLASSIC", "gameName": "teambuilder-match-4353501561", "gameStartTimestamp": 1656124229033, "gameType": "MATCHED_GAME", "gameVersion": "12.12.450.4196", "mapId": 11, "participants": [{"assists": 3, "baronKills": 0, "bountyLevel": 0, "challenges": {"12AssistStreakCount": 0, "abilityUses": 232, "acesBefore15Minutes": 0, "alliedJungleMonsterKills": 0, "baronTakedowns": 0, "blastConeOppositeOpponentCount": 0, "bountyGold": 150, "buffsStolen": 0, "completeSupportQuestInTime": 0, "controlWardTimeCoverageInRiverOrEnemyHalf": 0.19552200003697762, "controlWardsPlaced": 1, "damagePerMinute": 648.5823763050726, "damageTakenOnTeamPercentage": 0.16832478436196033, "dancedWithRiftHerald": 0, "deathsByEnemyChamps": 7, "dodgeSkillShotsSmallWindow": 4, "doubleAces": 0, "dragonTakedowns": 0, "earlyLaningPhaseGoldExpAdvantage": 0, "effectiveHealAndShielding": 0, "elderDragonKillsWithOpposingSoul": 0, "elderDragonMultikills": 0, "enemyChampionImmobilizations": 13, "enemyJungleMonsterKills": 0, "epicMonsterKillsNearEnemyJungler": 0, "epicMonsterKillsWithin30SecondsOfSpawn": 0, "epicMonsterSteals": 0, "epicMonsterStolenWithoutSmite": 0, "flawlessAces": 0, "fullTeamTakedown": 1, "gameLength": 1583.7581990769957, "getTakedownsInAllLanesEarlyJungleAsLaner": 0, "goldPerMinute": 320.04382458471366, "hadOpenNexus": 0, "immobilizeAndKillWithAlly": 0, "initialBuffCount": 0, "initialCrabCount": 0, "jungleCsBefore10Minutes": 0, "junglerTakedownsNearDamagedEpicMonster": 0, "kTurretsDestroyedBeforePlatesFall": 0, "kda": 0.7142857142857143, "killAfterHiddenWithAlly": 1, "killParticipation": 0.18518518518518517, "killedChampTookFullTeamDamageSurvived": 0, "killsNearEnemyTurret": 0, "killsOnOtherLanesEarlyJungleAsLaner": 1, "killsOnRecentlyHealedByAramPack": 0, "killsUnderOwnTurret": 0, "killsWithHelpFromEpicMonster": 1, "knockEnemyIntoTeamAndKill": 0, "landSkillShotsEarlyGame": 18, "laneMinionsFirst10Minutes": 68, "laningPhaseGoldExpAdvantage": 0, "legendaryCount": 0, "lostAnInhibitor": 0, "maxCsAdvantageOnLaneOpponent": 8, "maxKillDeficit": 0, "maxLevelLeadLaneOpponent": 1, "moreEnemyJungleThanOpponent": -129.00000005960464, "multiKillOneSpell": 0, "multiTurretRiftHeraldCount": 0, "multikills": 0, "multikillsAfterAggressiveFlash": 0, "mythicItemUsed": 6655, "outerTurretExecutesBefore10Minutes": 0, "outnumberedKills": 0, "outnumberedNexusKill": 0, "perfectDragonSoulsTaken": 0, "perfectGame": 0, "pickKillWithAlly": 3, "poroExplosions": 0, "quickCleanse": 0, "quickFirstTurret": 0, "quickSoloKills": 0, "riftHeraldTakedowns": 0, "saveAllyFromDeath": 0, "scuttleCrabKills": 0, "skillshotsDodged": 38, "skillshotsHit": 77, "snowballsHit": 0, "soloBaronKills": 0, "soloKills": 0, "soloTurretsLategame": 0, "stealthWardsPlaced": 6, "survivedSingleDigitHpCount": 0, "survivedThreeImmobilizesInFight": 0, "takedownOnFirstTurret": 0, "takedowns": 5, "takedownsAfterGainingLevelAdvantage": 1, "takedownsBeforeJungleMinionSpawn": 0, "takedownsFirstXMinutes": 1, "takedownsInAlcove": 0, "takedownsInEnemyFountain": 0, "teamBaronKills": 0, "teamDamagePercentage": 0.21326381014839293, "teamElderDragonKills": 0, "teamRiftHeraldKills": 1, "threeWardsOneSweeperCount": 0, "tookLargeDamageSurvived": 0, "turretPlatesTaken": 1, "turretTakedowns": 1, "turretsTakenWithRiftHerald": 0, "twentyMinionsIn3SecondsCount": 0, "unseenRecalls": 0, "visionScoreAdvantageLaneOpponent": 0.5319479703903198, "visionScorePerMinute": 0.6094404914112436, "wardTakedowns": 1, "wardTakedownsBefore20M": 0, "wardsGuarded": 0}, "champExperience": 11812, "champLevel": 14, "championId": 268, "championName": "Azir", "championTransform": 0, "consumablesPurchased": 4, "damageDealtToBuildings": 1994, "damageDealtToObjectives": 5029, "damageDealtToTurrets": 1994, "damageSelfMitigated": 9822, "deaths": 7, "detectorWardsPlaced": 1, "doubleKills": 0, "dragonKills": 0, "eligibleForProgression": true, "firstBloodAssist": false, "firstBloodKill": false, "firstTowerAssist": false, "firstTowerKill": false, "gameEndedInEarlySurrender": false, "gameEndedInSurrender": false, "goldEarned": 8447, "goldSpent": 7700, "individualPosition": "MIDDLE", "inhibitorKills": 0, "inhibitorTakedowns": 0, "inhibitorsLost": 1, "item0": 2055, "item1": 3102, "item2": 0, "item3": 6655, "item4": 3020, "item5": 1056, "item6": 3363, "itemsPurchased": 18, "killingSprees": 0, "kills": 2, "lane": "MIDDLE", "largestCriticalStrike": 0, "largestKillingSpree": 0, "largestMultiKill": 1, "longestTimeSpentLiving": 501, "magicDamageDealt": 97375, "magicDamageDealtToChampions": 16721, "magicDamageTaken": 7382, "neutralMinionsKilled": 0, "nexusKills": 0, "nexusLost": 1, "nexusTakedowns": 0, "objectivesStolen": 0, "objectivesStolenAssists": 0, "participantId": 1, "pentaKills": 0, "perks": {"statPerks": {"defense": 5002, "flex": 5008, "offense": 5005}, "styles": [{"description": "primaryStyle", "selections": [{"perk": 8214, "var1": 1510, "var2": 0, "var3": 0}, {"perk": 8226, "var1": 250, "var2": 1148, "var3": 0}, {"perk": 8210, "var1": 6, "var2": 0, "var3": 0}, {"perk": 8237, "var1": 603, "var2": 0, "var3": 0}], "style": 8200}, {"description": "subStyle", "selections": [{"perk": 8120, "var1": 5, "var2": 30, "var3": 5}, {"perk": 8134, "var1": 19, "var2": 5, "var3": 0}], "style": 8100}]}, "physicalDamageDealt": 5505, "physicalDamageDealtToChampions": 59, "physicalDamageTaken": 10376, "profileIcon": 3, "puuid": "7q4P678k91vcj4qQceUzO6PdTh7WImXg-ce_mn_jkBXoBBoTMTwrBulOKM1rcLMj4_5B28yAOX-tuw", "quadraKills": 0, "riotIdName": "", "riotIdTagline": "", "role": "CARRY", "sightWardsBoughtInGame": 0, "spell1Casts": 64, "spell2Casts": 154, "spell3Casts": 5, "spell4Casts": 9, "summoner1Casts": 2, "summoner1Id": 12, "summoner2Casts": 3, "summoner2Id": 4, "summonerId": "vYFiDBpXBZNdaup1fIFAJmD-yOU8N4mc0oVzdjuDn-vp5FE", "summonerLevel": 216, "summonerName": "1l1il1ili1", "teamEarlySurrendered": false, "teamId": 100, "teamPosition": "MIDDLE", "timeCCingOthers": 19, "timePlayed": 1583, "totalDamageDealt": 109723, "totalDamageDealtToChampions": 17119, "totalDamageShieldedOnTeammates": 0, "totalDamageTaken": 20079, "totalHeal": 1668, "totalHealsOnTeammates": 0, "totalMinionsKilled": 172, "totalTimeCCDealt": 185, "totalTimeSpentDead": 170, "totalUnitsHealed": 1, "tripleKills": 0, "trueDamageDealt": 6841, "trueDamageDealtToChampions": 338, "trueDamageTaken": 2320, "turretKills": 1, "turretTakedowns": 1, "turretsLost": 7, "unrealKills": 0, "visionScore": 16, "visionWardsBoughtInGame": 2, "wardsKilled": 1, "wardsPlaced": 11, "win": false}, {"assists": 5, "baronKills": 0, "bountyLevel": 0, "challenges": {"12AssistStreakCount": 0, "abilityUses": 254, "acesBefore15Minutes": 0, "alliedJungleMonsterKills": 90.00000017881393, "baronTakedowns": 0, "blastConeOppositeOpponentCount": 0, "bountyGold": 450, "buffsStolen": 0, "completeSupportQuestInTime": 0, "controlWardsPlaced": 0, "damagePerMinute": 826.9088258395382, "damageTakenOnTeamPercentage": 0.2884022381588496, "dancedWithRiftHerald": 0, "deathsByEnemyChamps": 4, "dodgeSkillShotsSmallWindow": 17, "doubleAces": 0, "dragonTakedowns": 1, "earliestDragonTakedown": 1243.9992168908286, "earlyLaningPhaseGoldExpAdvantage": 0, "effectiveHealAndShielding": 0, "elderDragonKillsWithOpposingSoul": 0, "elderDragonMultikills": 0, "enemyChampionImmobilizations": 6, "enemyJungleMonsterKills": 1.2000000178813934, "epicMonsterKillsNearEnemyJungler": 1, "epicMonsterKillsWithin30SecondsOfSpawn": 0, "epicMonsterSteals": 0, "epicMonsterStolenWithoutSmite": 0, "fastestLegendary": 810.8026952640903, "flawlessAces": 0, "fullTeamTakedown": 1, "gameLength": 1583.7581990769957, "goldPerMinute": 485.08459161662756, "hadOpenNexus": 0, "highestCrowdControlScore": 1, "immobilizeAndKillWithAlly": 3, "initialBuffCount": 2, "initialCrabCount": 0, "jungleCsBefore10Minutes": 44.00000008940697, "junglerKillsEarlyJungle": 0, "junglerTakedownsNearDamagedEpicMonster": 1, "kTurretsDestroyedBeforePlatesFall": 0, "kda": 4.75, "killAfterHiddenWithAlly": 0, "killParticipation": 0.7037037037037037, "killedChampTookFullTeamDamageSurvived": 0, "killsNearEnemyTurret": 0, "killsOnLanersEarlyJungleAsJungler": 3, "killsOnRecentlyHealedByAramPack": 0, "killsUnderOwnTurret": 4, "killsWithHelpFromEpicMonster": 0, "knockEnemyIntoTeamAndKill": 0, "landSkillShotsEarlyGame": 2, "laneMinionsFirst10Minutes": 14, "laningPhaseGoldExpAdvantage": 0, "legendaryCount": 1, "lostAnInhibitor": 0, "maxCsAdvantageOnLaneOpponent": 4, "maxKillDeficit": 0, "maxLevelLeadLaneOpponent": 2, "moreEnemyJungleThanOpponent": -84.99999997019768, "multiKillOneSpell": 0, "multiTurretRiftHeraldCount": 0, "multikills": 4, "multikillsAfterAggressiveFlash": 0, "mythicItemUsed": 6653, "outerTurretExecutesBefore10Minutes": 0, "outnumberedKills": 1, "outnumberedNexusKill": 0, "perfectDragonSoulsTaken": 0, "perfectGame": 0, "pickKillWithAlly": 13, "poroExplosions": 0, "quickCleanse": 0, "quickFirstTurret": 0, "quickSoloKills": 0, "riftHeraldTakedowns": 1, "saveAllyFromDeath": 0, "scuttleCrabKills": 1, "skillshotsDodged": 105, "skillshotsHit": 16, "snowballsHit": 0, "soloBaronKills": 0, "soloKills": 4, "soloTurretsLategame": 0, "stealthWardsPlaced": 1, "survivedSingleDigitHpCount": 0, "survivedThreeImmobilizesInFight": 0, "takedownOnFirstTurret": 1, "takedowns": 19, "takedownsAfterGainingLevelAdvantage": 0, "takedownsBeforeJungleMinionSpawn": 0, "takedownsFirstXMinutes": 11, "takedownsInAlcove": 0, "takedownsInEnemyFountain": 0, "teamBaronKills": 0, "teamDamagePercentage": 0.2719002755648798, "teamElderDragonKills": 0, "teamRiftHeraldKills": 1, "threeWardsOneSweeperCount": 0, "tookLargeDamageSurvived": 0, "turretPlatesTaken": 0, "turretTakedowns": 1, "turretsTakenWithRiftHerald": 0, "twentyMinionsIn3SecondsCount": 0, "unseenRecalls": 0, "visionScoreAdvantageLaneOpponent": -0.43892520666122437, "visionScorePerMinute": 0.7407510731853136, "wardTakedowns": 6, "wardTakedownsBefore20M": 2, "wardsGuarded": 0}, "champExperience": 12318, "champLevel": 14, "championId": 876, "championName": "Lillia", "championTransform": 0, "consumablesPurchased": 0, "damageDealtToBuildings": 326, "damageDealtToObjectives": 18108, "damageDealtToTurrets": 326, "damageSelfMitigated": 22226, "deaths": 4, "detectorWardsPlaced": 0, "doubleKills": 3, "dragonKills": 1, "eligibleForProgression": true, "firstBloodAssist": false, "firstBloodKill": false, "firstTowerAssist": false, "firstTowerKill": false, "gameEndedInEarlySurrender": false, "gameEndedInSurrender": false, "goldEarned": 12804, "goldSpent": 11750, "individualPosition": "JUNGLE", "inhibitorKills": 0, "inhibitorTakedowns": 0, "inhibitorsLost": 1, "item0": 6653, "item1": 4637, "item2": 3047, "item3": 1082, "item4": 3116, "item5": 3082, "item6": 3364, "itemsPurchased": 18, "killingSprees": 1, "kills": 14, "lane": "JUNGLE", "largestCriticalStrike": 0, "largestKillingSpree": 13, "largestMultiKill": 3, "longestTimeSpentLiving": 1087, "magicDamageDealt": 99817, "magicDamageDealtToChampions": 15008, "magicDamageTaken": 10622, "neutralMinionsKilled": 113, "nexusKills": 0, "nexusLost": 1, "nexusTakedowns": 0, "objectivesStolen": 0, "objectivesStolenAssists": 0, "participantId": 2, "pentaKills": 0, "perks": {"statPerks": {"defense": 5003, "flex": 5008, "offense": 5008}, "styles": [{"description": "primaryStyle", "selections": [{"perk": 8010, "var1": 155, "var2": 0, "var3": 0}, {"perk": 9111, "var1": 1192, "var2": 380, "var3": 0}, {"perk": 9105, "var1": 11, "var2": 0, "var3": 0}, {"perk": 8299, "var1": 557, "var2": 0, "var3": 0}], "style": 8000}, {"description": "subStyle", "selections": [{"perk": 8429, "var1": 54, "var2": 15, "var3": 12}, {"perk": 8451, "var1": 168, "var2": 0, "var3": 0}], "style": 8400}]}, "physicalDamageDealt": 13117, "physicalDamageDealtToChampions": 1436, "physicalDamageTaken": 18153, "profileIcon": 1298, "puuid": "C0t14iPbMv-GcaamUzSFVKEyJNOiPIntPymyR84i8ZfsPH6PRZppSNxM9hYHrPpeauCSYpJiNWwZ0w", "quadraKills": 0, "riotIdName": "", "riotIdTagline": "", "role": "NONE", "sightWardsBoughtInGame": 0, "spell1Casts": 131, "spell2Casts": 49, "spell3Casts": 66, "spell4Casts": 8, "summoner1Casts": 4, "summoner1Id": 4, "summoner2Casts": 11, "summoner2Id": 11, "summonerId": "-kgnTWNGi7Vv1h2jPLdAUefVlaeypba6fUitZWQAOWy5gnuyYpunvU3Isg", "summonerLevel": 246, "summonerName": "G\u00ecrelle", "teamEarlySurrendered": false, "teamId": 100, "teamPosition": "JUNGLE", "timeCCingOthers": 27, "timePlayed": 1583, "totalDamageDealt": 146570, "totalDamageDealtToChampions": 21827, "totalDamageShieldedOnTeammates": 0, "totalDamageTaken": 34402, "totalHeal": 13005, "totalHealsOnTeammates": 0, "totalMinionsKilled": 51, "totalTimeCCDealt": 578, "totalTimeSpentDead": 126, "totalUnitsHealed": 1, "tripleKills": 1, "trueDamageDealt": 33634, "trueDamageDealtToChampions": 5381, "trueDamageTaken": 5627, "turretKills": 0, "turretTakedowns": 1, "turretsLost": 7, "unrealKills": 0, "visionScore": 19, "visionWardsBoughtInGame": 0, "wardsKilled": 6, "wardsPlaced": 1, "win": false}, {"assists": 8, "baronKills": 0, "bountyLevel": 0, "challenges": {"12AssistStreakCount": 0, "abilityUses": 90, "acesBefore15Minutes": 0, "alliedJungleMonsterKills": 9.500000029802322, "baronTakedowns": 0, "blastConeOppositeOpponentCount": 0, "bountyGold": 825, "buffsStolen": 0, "completeSupportQuestInTime": 0, "controlWardsPlaced": 0, "damagePerMinute": 1035.6639112545224, "damageTakenOnTeamPercentage": 0.1640265384190248, "dancedWithRiftHerald": 0, "deathsByEnemyChamps": 9, "dodgeSkillShotsSmallWindow": 13, "doubleAces": 0, "dragonTakedowns": 0, "earlyLaningPhaseGoldExpAdvantage": 0, "effectiveHealAndShielding": 0, "elderDragonKillsWithOpposingSoul": 0, "elderDragonMultikills": 0, "enemyChampionImmobilizations": 0, "enemyJungleMonsterKills": 0.4000000059604645, "epicMonsterKillsNearEnemyJungler": 0, "epicMonsterKillsWithin30SecondsOfSpawn": 0, "epicMonsterSteals": 0, "epicMonsterStolenWithoutSmite": 0, "flawlessAces": 0, "fullTeamTakedown": 1, "gameLength": 1583.7581990769957, "getTakedownsInAllLanesEarlyJungleAsLaner": 0, "goldPerMinute": 450.14177231835816, "hadOpenNexus": 0, "highestChampionDamage": 1, "immobilizeAndKillWithAlly": 0, "initialBuffCount": 0, "initialCrabCount": 0, "jungleCsBefore10Minutes": 0, "junglerTakedownsNearDamagedEpicMonster": 0, "kTurretsDestroyedBeforePlatesFall": 0, "kda": 1.7777777777777777, "killAfterHiddenWithAlly": 0, "killParticipation": 0.5925925925925926, "killedChampTookFullTeamDamageSurvived": 0, "killsNearEnemyTurret": 2, "killsOnOtherLanesEarlyJungleAsLaner": 0, "killsOnRecentlyHealedByAramPack": 0, "killsUnderOwnTurret": 0, "killsWithHelpFromEpicMonster": 0, "knockEnemyIntoTeamAndKill": 0, "landSkillShotsEarlyGame": 1, "laneMinionsFirst10Minutes": 53, "laningPhaseGoldExpAdvantage": 0, "legendaryCount": 0, "lostAnInhibitor": 0, "maxCsAdvantageOnLaneOpponent": 23.400000005960464, "maxKillDeficit": 0, "maxLevelLeadLaneOpponent": 2, "moreEnemyJungleThanOpponent": -129.00000005960464, "multiKillOneSpell": 0, "multiTurretRiftHeraldCount": 0, "multikills": 1, "multikillsAfterAggressiveFlash": 0, "mythicItemUsed": 6672, "outerTurretExecutesBefore10Minutes": 0, "outnumberedKills": 3, "outnumberedNexusKill": 0, "perfectDragonSoulsTaken": 0, "perfectGame": 0, "pickKillWithAlly": 10, "poroExplosions": 0, "quickCleanse": 0, "quickFirstTurret": 0, "quickSoloKills": 0, "riftHeraldTakedowns": 0, "saveAllyFromDeath": 0, "scuttleCrabKills": 0, "skillshotsDodged": 99, "skillshotsHit": 5, "snowballsHit": 0, "soloBaronKills": 0, "soloKills": 2, "soloTurretsLategame": 0, "stealthWardsPlaced": 4, "survivedSingleDigitHpCount": 0, "survivedThreeImmobilizesInFight": 0, "takedownOnFirstTurret": 1, "takedowns": 16, "takedownsAfterGainingLevelAdvantage": 0, "takedownsBeforeJungleMinionSpawn": 0, "takedownsFirstXMinutes": 2, "takedownsInAlcove": 0, "takedownsInEnemyFountain": 0, "teamBaronKills": 0, "teamDamagePercentage": 0.3405421420878024, "teamElderDragonKills": 0, "teamRiftHeraldKills": 1, "threeWardsOneSweeperCount": 0, "tookLargeDamageSurvived": 0, "turretPlatesTaken": 2, "turretTakedowns": 1, "turretsTakenWithRiftHerald": 0, "twentyMinionsIn3SecondsCount": 0, "unseenRecalls": 0, "visionScoreAdvantageLaneOpponent": -0.6576202511787415, "visionScorePerMinute": 0.25549443066458466, "wardTakedowns": 0, "wardTakedownsBefore20M": 0, "wardsGuarded": 0}, "champExperience": 12057, "champLevel": 14, "championId": 29, "championName": "Twitch", "championTransform": 0, "consumablesPurchased": 7, "damageDealtToBuildings": 2232, "damageDealtToObjectives": 4131, "damageDealtToTurrets": 2232, "damageSelfMitigated": 8956, "deaths": 9, "detectorWardsPlaced": 0, "doubleKills": 1, "dragonKills": 0, "eligibleForProgression": true, "firstBloodAssist": false, "firstBloodKill": false, "firstTowerAssist": false, "firstTowerKill": false, "gameEndedInEarlySurrender": false, "gameEndedInSurrender": false, "goldEarned": 11881, "goldSpent": 10650, "individualPosition": "BOTTOM", "inhibitorKills": 0, "inhibitorTakedowns": 0, "inhibitorsLost": 1, "item0": 3153, "item1": 3006, "item2": 6672, "item3": 3085, "item4": 0, "item5": 0, "item6": 3340, "itemsPurchased": 31, "killingSprees": 3, "kills": 8, "lane": "BOTTOM", "largestCriticalStrike": 465, "largestKillingSpree": 2, "largestMultiKill": 2, "longestTimeSpentLiving": 291, "magicDamageDealt": 520, "magicDamageDealtToChampions": 520, "magicDamageTaken": 5798, "neutralMinionsKilled": 12, "nexusKills": 0, "nexusLost": 1, "nexusTakedowns": 0, "objectivesStolen": 0, "objectivesStolenAssists": 0, "participantId": 3, "pentaKills": 0, "perks": {"statPerks": {"defense": 5002, "flex": 5008, "offense": 5005}, "styles": [{"description": "primaryStyle", "selections": [{"perk": 8005, "var1": 1504, "var2": 806, "var3": 698}, {"perk": 8009, "var1": 1882, "var2": 0, "var3": 0}, {"perk": 9104, "var1": 17, "var2": 20, "var3": 0}, {"perk": 8014, "var1": 513, "var2": 0, "var3": 0}], "style": 8000}, {"description": "subStyle", "selections": [{"perk": 8138, "var1": 18, "var2": 0, "var3": 0}, {"perk": 8135, "var1": 400, "var2": 5, "var3": 0}], "style": 8100}]}, "physicalDamageDealt": 97151, "physicalDamageDealtToChampions": 22620, "physicalDamageTaken": 12537, "profileIcon": 691, "puuid": "lu42OafJKXsa8E6Y645gT0iupCsyswCRAoc_r4cI0WYWG2AH1mxDFS9vK9Qg6SZFkE5pOvknRvtl0g", "quadraKills": 0, "riotIdName": "", "riotIdTagline": "", "role": "SOLO", "sightWardsBoughtInGame": 0, "spell1Casts": 30, "spell2Casts": 25, "spell3Casts": 24, "spell4Casts": 11, "summoner1Casts": 4, "summoner1Id": 4, "summoner2Casts": 4, "summoner2Id": 3, "summonerId": "lyaZoNPkwnk7Lf_ZiQMXRJcT8u9FwvIrMK6619Vl5Vo3o6A", "summonerLevel": 326, "summonerName": " Cabbag\u00e9", "teamEarlySurrendered": false, "teamId": 100, "teamPosition": "BOTTOM", "timeCCingOthers": 10, "timePlayed": 1583, "totalDamageDealt": 108649, "totalDamageDealtToChampions": 27337, "totalDamageShieldedOnTeammates": 0, "totalDamageTaken": 19566, "totalHeal": 0, "totalHealsOnTeammates": 0, "totalMinionsKilled": 141, "totalTimeCCDealt": 225, "totalTimeSpentDead": 236, "totalUnitsHealed": 0, "tripleKills": 0, "trueDamageDealt": 10978, "trueDamageDealtToChampions": 4197, "trueDamageTaken": 1230, "turretKills": 0, "turretTakedowns": 1, "turretsLost": 7, "unrealKills": 0, "visionScore": 6, "visionWardsBoughtInGame": 0, "wardsKilled": 0, "wardsPlaced": 4, "win": false}, {"assists": 9, "baronKills": 0, "bountyLevel": 0, "challenges": {"12AssistStreakCount": 0, "abilityUses": 180, "acesBefore15Minutes": 0, "alliedJungleMonsterKills": 0, "baronTakedowns": 0, "blastConeOppositeOpponentCount": 0, "bountyGold": 0, "buffsStolen": 0, "completeSupportQuestInTime": 0, "controlWardsPlaced": 0, "damagePerMinute": 410.1333345131566, "damageTakenOnTeamPercentage": 0.2391981554465671, "dancedWithRiftHerald": 0, "deathsByEnemyChamps": 6, "dodgeSkillShotsSmallWindow": 27, "doubleAces": 0, "dragonTakedowns": 0, "earlyLaningPhaseGoldExpAdvantage": 0, "effectiveHealAndShielding": 0, "elderDragonKillsWithOpposingSoul": 0, "elderDragonMultikills": 0, "enemyChampionImmobilizations": 0, "enemyJungleMonsterKills": 2, "epicMonsterKillsNearEnemyJungler": 0, "epicMonsterKillsWithin30SecondsOfSpawn": 0, "epicMonsterSteals": 0, "epicMonsterStolenWithoutSmite": 0, "flawlessAces": 0, "fullTeamTakedown": 1, "gameLength": 1583.7581990769957, "getTakedownsInAllLanesEarlyJungleAsLaner": 0, "goldPerMinute": 270.2654590632624, "hadOpenNexus": 0, "immobilizeAndKillWithAlly": 0, "initialBuffCount": 0, "initialCrabCount": 0, "jungleCsBefore10Minutes": 0, "junglerTakedownsNearDamagedEpicMonster": 0, "kTurretsDestroyedBeforePlatesFall": 0, "kda": 1.8333333333333333, "killAfterHiddenWithAlly": 0, "killParticipation": 0.4074074074074074, "killedChampTookFullTeamDamageSurvived": 0, "killsNearEnemyTurret": 0, "killsOnOtherLanesEarlyJungleAsLaner": 0, "killsOnRecentlyHealedByAramPack": 0, "killsUnderOwnTurret": 0, "killsWithHelpFromEpicMonster": 0, "knockEnemyIntoTeamAndKill": 0, "landSkillShotsEarlyGame": 0, "laneMinionsFirst10Minutes": 40, "laningPhaseGoldExpAdvantage": 0, "legendaryCount": 0, "lostAnInhibitor": 0, "maxCsAdvantageOnLaneOpponent": 1, "maxKillDeficit": 0, "maxLevelLeadLaneOpponent": 1, "moreEnemyJungleThanOpponent": -129.00000005960464, "multiKillOneSpell": 0, "multiTurretRiftHeraldCount": 0, "multikills": 0, "multikillsAfterAggressiveFlash": 0, "mythicItemUsed": 3078, "outerTurretExecutesBefore10Minutes": 0, "outnumberedKills": 0, "outnumberedNexusKill": 0, "perfectDragonSoulsTaken": 0, "perfectGame": 0, "pickKillWithAlly": 9, "poroExplosions": 0, "quickCleanse": 0, "quickFirstTurret": 0, "quickSoloKills": 0, "riftHeraldTakedowns": 0, "saveAllyFromDeath": 0, "scuttleCrabKills": 0, "skillshotsDodged": 152, "skillshotsHit": 1, "snowballsHit": 0, "soloBaronKills": 0, "soloKills": 0, "soloTurretsLategame": 0, "stealthWardsPlaced": 2, "survivedSingleDigitHpCount": 0, "survivedThreeImmobilizesInFight": 0, "takedownOnFirstTurret": 0, "takedowns": 11, "takedownsAfterGainingLevelAdvantage": 0, "takedownsBeforeJungleMinionSpawn": 0, "takedownsFirstXMinutes": 4, "takedownsInAlcove": 0, "takedownsInEnemyFountain": 0, "teamBaronKills": 0, "teamDamagePercentage": 0.1348581163821196, "teamElderDragonKills": 0, "teamRiftHeraldKills": 1, "threeWardsOneSweeperCount": 0, "tookLargeDamageSurvived": 0, "turretPlatesTaken": 0, "turretTakedowns": 1, "turretsTakenWithRiftHerald": 0, "twentyMinionsIn3SecondsCount": 0, "unseenRecalls": 0, "visionScoreAdvantageLaneOpponent": -0.7405523061752319, "visionScorePerMinute": 0.18884863030823767, "wardTakedowns": 1, "wardTakedownsBefore20M": 0, "wardsGuarded": 0}, "champExperience": 9659, "champLevel": 12, "championId": 75, "championName": "Nasus", "championTransform": 0, "consumablesPurchased": 1, "damageDealtToBuildings": 816, "damageDealtToObjectives": 824, "damageDealtToTurrets": 816, "damageSelfMitigated": 21375, "deaths": 6, "detectorWardsPlaced": 0, "doubleKills": 0, "dragonKills": 0, "eligibleForProgression": true, "firstBloodAssist": false, "firstBloodKill": false, "firstTowerAssist": false, "firstTowerKill": false, "gameEndedInEarlySurrender": false, "gameEndedInSurrender": false, "goldEarned": 7133, "goldSpent": 6883, "individualPosition": "TOP", "inhibitorKills": 0, "inhibitorTakedowns": 0, "inhibitorsLost": 1, "item0": 3105, "item1": 3078, "item2": 3070, "item3": 3158, "item4": 1054, "item5": 1029, "item6": 3340, "itemsPurchased": 16, "killingSprees": 1, "kills": 2, "lane": "TOP", "largestCriticalStrike": 0, "largestKillingSpree": 2, "largestMultiKill": 1, "longestTimeSpentLiving": 836, "magicDamageDealt": 10538, "magicDamageDealtToChampions": 3209, "magicDamageTaken": 11624, "neutralMinionsKilled": 2, "nexusKills": 0, "nexusLost": 1, "nexusTakedowns": 0, "objectivesStolen": 0, "objectivesStolenAssists": 0, "participantId": 4, "pentaKills": 0, "perks": {"statPerks": {"defense": 5002, "flex": 5003, "offense": 5007}, "styles": [{"description": "primaryStyle", "selections": [{"perk": 8021, "var1": 1045, "var2": 1012, "var3": 0}, {"perk": 9111, "var1": 587, "var2": 220, "var3": 0}, {"perk": 9105, "var1": 17, "var2": 20, "var3": 0}, {"perk": 8299, "var1": 502, "var2": 0, "var3": 0}], "style": 8000}, {"description": "subStyle", "selections": [{"perk": 8444, "var1": 1581, "var2": 0, "var3": 0}, {"perk": 8242, "var1": 91, "var2": 0, "var3": 0}], "style": 8400}]}, "physicalDamageDealt": 45796, "physicalDamageDealtToChampions": 7548, "physicalDamageTaken": 13159, "profileIcon": 1597, "puuid": "oCsRQGGyIsQojXmeuWwzBaOQ_kvQp-D4EQgsPpSLL2Ucwi18Mq8cJxCrtmhbQSwVtLjO-MGQUP6jZw", "quadraKills": 0, "riotIdName": "", "riotIdTagline": "", "role": "SOLO", "sightWardsBoughtInGame": 0, "spell1Casts": 110, "spell2Casts": 28, "spell3Casts": 32, "spell4Casts": 10, "summoner1Casts": 3, "summoner1Id": 4, "summoner2Casts": 5, "summoner2Id": 6, "summonerId": "wP6EDf557QKQBwOJhL4wJN7xlMyYKDvAsmrSVTN2qMzY9u3k", "summonerLevel": 398, "summonerName": "Laaemel", "teamEarlySurrendered": false, "teamId": 100, "teamPosition": "TOP", "timeCCingOthers": 14, "timePlayed": 1583, "totalDamageDealt": 57913, "totalDamageDealtToChampions": 10825, "totalDamageShieldedOnTeammates": 0, "totalDamageTaken": 28533, "totalHeal": 1540, "totalHealsOnTeammates": 0, "totalMinionsKilled": 95, "totalTimeCCDealt": 89, "totalTimeSpentDead": 223, "totalUnitsHealed": 1, "tripleKills": 0, "trueDamageDealt": 1578, "trueDamageDealtToChampions": 68, "trueDamageTaken": 3749, "turretKills": 1, "turretTakedowns": 1, "turretsLost": 7, "unrealKills": 0, "visionScore": 4, "visionWardsBoughtInGame": 0, "wardsKilled": 1, "wardsPlaced": 2, "win": false}, {"assists": 17, "baronKills": 0, "bountyLevel": 0, "challenges": {"12AssistStreakCount": 1, "abilityUses": 181, "acesBefore15Minutes": 0, "alliedJungleMonsterKills": 0, "baronTakedowns": 0, "blastConeOppositeOpponentCount": 0, "bountyGold": 0, "buffsStolen": 0, "completeSupportQuestInTime": 0, "controlWardTimeCoverageInRiverOrEnemyHalf": 0.1918697068874025, "controlWardsPlaced": 8, "damagePerMinute": 119.9325443122083, "damageTakenOnTeamPercentage": 0.1400482836135982, "dancedWithRiftHerald": 0, "deathsByEnemyChamps": 7, "dodgeSkillShotsSmallWindow": 10, "doubleAces": 0, "dragonTakedowns": 1, "earliestDragonTakedown": 1243.9992168908286, "earlyLaningPhaseGoldExpAdvantage": 0, "effectiveHealAndShielding": 6233.51171875, "elderDragonKillsWithOpposingSoul": 0, "elderDragonMultikills": 0, "enemyChampionImmobilizations": 26, "enemyJungleMonsterKills": 0, "epicMonsterKillsNearEnemyJungler": 0, "epicMonsterKillsWithin30SecondsOfSpawn": 0, "epicMonsterSteals": 0, "epicMonsterStolenWithoutSmite": 0, "flawlessAces": 0, "fullTeamTakedown": 1, "gameLength": 1583.7581990769957, "getTakedownsInAllLanesEarlyJungleAsLaner": 0, "goldPerMinute": 261.61519800511337, "hadOpenNexus": 0, "highestWardKills": 1, "immobilizeAndKillWithAlly": 5, "initialBuffCount": 0, "initialCrabCount": 0, "jungleCsBefore10Minutes": 0, "junglerTakedownsNearDamagedEpicMonster": 0, "kTurretsDestroyedBeforePlatesFall": 0, "kda": 2.5714285714285716, "killAfterHiddenWithAlly": 1, "killParticipation": 0.6666666666666666, "killedChampTookFullTeamDamageSurvived": 0, "killsNearEnemyTurret": 0, "killsOnOtherLanesEarlyJungleAsLaner": 0, "killsOnRecentlyHealedByAramPack": 0, "killsUnderOwnTurret": 0, "killsWithHelpFromEpicMonster": 0, "knockEnemyIntoTeamAndKill": 2, "landSkillShotsEarlyGame": 15, "laneMinionsFirst10Minutes": 3, "laningPhaseGoldExpAdvantage": 0, "legendaryCount": 0, "lostAnInhibitor": 0, "maxCsAdvantageOnLaneOpponent": 0, "maxKillDeficit": 0, "maxLevelLeadLaneOpponent": 1, "moreEnemyJungleThanOpponent": -129.00000005960464, "multiKillOneSpell": 0, "multiTurretRiftHeraldCount": 0, "multikills": 0, "multikillsAfterAggressiveFlash": 0, "mythicItemUsed": 2065, "outerTurretExecutesBefore10Minutes": 0, "outnumberedKills": 0, "outnumberedNexusKill": 0, "perfectDragonSoulsTaken": 0, "perfectGame": 0, "pickKillWithAlly": 14, "poroExplosions": 0, "quickCleanse": 0, "quickFirstTurret": 0, "quickSoloKills": 0, "riftHeraldTakedowns": 1, "saveAllyFromDeath": 1, "scuttleCrabKills": 0, "skillshotsDodged": 69, "skillshotsHit": 44, "snowballsHit": 0, "soloBaronKills": 0, "soloKills": 0, "soloTurretsLategame": 0, "stealthWardsPlaced": 18, "survivedSingleDigitHpCount": 0, "survivedThreeImmobilizesInFight": 0, "takedownOnFirstTurret": 1, "takedowns": 18, "takedownsAfterGainingLevelAdvantage": 0, "takedownsBeforeJungleMinionSpawn": 0, "takedownsFirstXMinutes": 6, "takedownsInAlcove": 0, "takedownsInEnemyFountain": 0, "teamBaronKills": 0, "teamDamagePercentage": 0.03943565581680526, "teamElderDragonKills": 0, "teamRiftHeraldKills": 1, "threeWardsOneSweeperCount": 0, "tookLargeDamageSurvived": 0, "turretPlatesTaken": 0, "turretTakedowns": 1, "turretsTakenWithRiftHerald": 0, "twentyMinionsIn3SecondsCount": 0, "unseenRecalls": 0, "visionScoreAdvantageLaneOpponent": 0.39146411418914795, "visionScorePerMinute": 2.4234066868274162, "wardTakedowns": 12, "wardTakedownsBefore20M": 9, "wardsGuarded": 0}, "champExperience": 8845, "champLevel": 12, "championId": 40, "championName": "Janna", "championTransform": 0, "consumablesPurchased": 12, "damageDealtToBuildings": 0, "damageDealtToObjectives": 2236, "damageDealtToTurrets": 0, "damageSelfMitigated": 9149, "deaths": 7, "detectorWardsPlaced": 8, "doubleKills": 0, "dragonKills": 0, "eligibleForProgression": true, "firstBloodAssist": false, "firstBloodKill": false, "firstTowerAssist": false, "firstTowerKill": false, "gameEndedInEarlySurrender": false, "gameEndedInSurrender": false, "goldEarned": 6905, "goldSpent": 5835, "individualPosition": "UTILITY", "inhibitorKills": 0, "inhibitorTakedowns": 0, "inhibitorsLost": 1, "item0": 3853, "item1": 0, "item2": 2065, "item3": 3117, "item4": 1052, "item5": 3114, "item6": 3364, "itemsPurchased": 26, "killingSprees": 0, "kills": 1, "lane": "MIDDLE", "largestCriticalStrike": 0, "largestKillingSpree": 0, "largestMultiKill": 1, "longestTimeSpentLiving": 775, "magicDamageDealt": 9905, "magicDamageDealtToChampions": 2875, "magicDamageTaken": 6572, "neutralMinionsKilled": 0, "nexusKills": 0, "nexusLost": 1, "nexusTakedowns": 0, "objectivesStolen": 0, "objectivesStolenAssists": 0, "participantId": 5, "pentaKills": 0, "perks": {"statPerks": {"defense": 5002, "flex": 5008, "offense": 5008}, "styles": [{"description": "primaryStyle", "selections": [{"perk": 8214, "var1": 438, "var2": 1035, "var3": 0}, {"perk": 8226, "var1": 250, "var2": 471, "var3": 0}, {"perk": 8210, "var1": 3, "var2": 0, "var3": 0}, {"perk": 8236, "var1": 24, "var2": 0, "var3": 0}], "style": 8200}, {"description": "subStyle", "selections": [{"perk": 8105, "var1": 13, "var2": 5, "var3": 0}, {"perk": 8120, "var1": 3, "var2": 30, "var3": 8}], "style": 8100}]}, "physicalDamageDealt": 2031, "physicalDamageDealtToChampions": 282, "physicalDamageTaken": 7832, "profileIcon": 1110, "puuid": "Y9Ohd25EirbZYITMPCqOhlTta4hBy-fA9R_H1hPuia6LRTX_z0Z1Xnm_g-DQ2URSZ-E5-vcPQ-mhwg", "quadraKills": 0, "riotIdName": "", "riotIdTagline": "", "role": "SUPPORT", "sightWardsBoughtInGame": 0, "spell1Casts": 103, "spell2Casts": 27, "spell3Casts": 46, "spell4Casts": 5, "summoner1Casts": 4, "summoner1Id": 4, "summoner2Casts": 4, "summoner2Id": 7, "summonerId": "QFJLaFOGjJEN5YyhqX1XBW5FpVvNGKNNflrhfKqpd-Bw-7U", "summonerLevel": 330, "summonerName": "Hadoku", "teamEarlySurrendered": false, "teamId": 100, "teamPosition": "UTILITY", "timeCCingOthers": 26, "timePlayed": 1583, "totalDamageDealt": 13369, "totalDamageDealtToChampions": 3165, "totalDamageShieldedOnTeammates": 4284, "totalDamageTaken": 16706, "totalHeal": 4115, "totalHealsOnTeammates": 1949, "totalMinionsKilled": 19, "totalTimeCCDealt": 128, "totalTimeSpentDead": 169, "totalUnitsHealed": 4, "tripleKills": 0, "trueDamageDealt": 1432, "trueDamageDealtToChampions": 7, "trueDamageTaken": 2300, "turretKills": 0, "turretTakedowns": 1, "turretsLost": 7, "unrealKills": 0, "visionScore": 63, "visionWardsBoughtInGame": 10, "wardsKilled": 12, "wardsPlaced": 26, "win": false}, {"assists": 8, "baronKills": 0, "bountyLevel": 1, "challenges": {"12AssistStreakCount": 0, "abilityUses": 136, "acesBefore15Minutes": 0, "alliedJungleMonsterKills": 0, "baronBuffGoldAdvantageOverThreshold": 1, "baronTakedowns": 0, "blastConeOppositeOpponentCount": 0, "bountyGold": 0, "buffsStolen": 0, "completeSupportQuestInTime": 0, "controlWardsPlaced": 1, "damagePerMinute": 747.1508527956626, "damageTakenOnTeamPercentage": 0.16343295298968685, "dancedWithRiftHerald": 0, "deathsByEnemyChamps": 7, "dodgeSkillShotsSmallWindow": 0, "doubleAces": 0, "dragonTakedowns": 0, "earliestBaron": 1352.9953731933367, "earlyLaningPhaseGoldExpAdvantage": 0, "effectiveHealAndShielding": 0, "elderDragonKillsWithOpposingSoul": 0, "elderDragonMultikills": 0, "enemyChampionImmobilizations": 35, "enemyJungleMonsterKills": 0, "epicMonsterKillsNearEnemyJungler": 0, "epicMonsterKillsWithin30SecondsOfSpawn": 0, "epicMonsterSteals": 0, "epicMonsterStolenWithoutSmite": 0, "firstTurretKilledTime": 974.2083484759784, "flawlessAces": 0, "fullTeamTakedown": 1, "gameLength": 1583.7581990769957, "getTakedownsInAllLanesEarlyJungleAsLaner": 0, "goldPerMinute": 345.2695103882873, "hadOpenNexus": 0, "immobilizeAndKillWithAlly": 5, "initialBuffCount": 0, "initialCrabCount": 0, "jungleCsBefore10Minutes": 0, "junglerTakedownsNearDamagedEpicMonster": 0, "kTurretsDestroyedBeforePlatesFall": 0, "kda": 1.5714285714285714, "killAfterHiddenWithAlly": 0, "killParticipation": 0.3333333333333333, "killedChampTookFullTeamDamageSurvived": 0, "killsNearEnemyTurret": 1, "killsOnOtherLanesEarlyJungleAsLaner": 0, "killsOnRecentlyHealedByAramPack": 0, "killsUnderOwnTurret": 0, "killsWithHelpFromEpicMonster": 0, "knockEnemyIntoTeamAndKill": 0, "landSkillShotsEarlyGame": 20, "laneMinionsFirst10Minutes": 67, "laningPhaseGoldExpAdvantage": 0, "legendaryCount": 0, "lostAnInhibitor": 0, "maxCsAdvantageOnLaneOpponent": 40, "maxKillDeficit": 5, "maxLevelLeadLaneOpponent": 2, "moreEnemyJungleThanOpponent": -109.00000008940697, "multiKillOneSpell": 0, "multiTurretRiftHeraldCount": 0, "multikills": 0, "multikillsAfterAggressiveFlash": 0, "outerTurretExecutesBefore10Minutes": 0, "outnumberedKills": 1, "outnumberedNexusKill": 0, "perfectDragonSoulsTaken": 0, "perfectGame": 0, "pickKillWithAlly": 8, "poroExplosions": 0, "quickCleanse": 0, "quickFirstTurret": 0, "quickSoloKills": 0, "riftHeraldTakedowns": 0, "saveAllyFromDeath": 0, "scuttleCrabKills": 1, "skillshotsDodged": 11, "skillshotsHit": 66, "snowballsHit": 0, "soloBaronKills": 0, "soloKills": 0, "soloTurretsLategame": 0, "stealthWardsPlaced": 8, "survivedSingleDigitHpCount": 0, "survivedThreeImmobilizesInFight": 0, "takedownOnFirstTurret": 1, "takedowns": 11, "takedownsAfterGainingLevelAdvantage": 0, "takedownsBeforeJungleMinionSpawn": 1, "takedownsFirstXMinutes": 2, "takedownsInAlcove": 0, "takedownsInEnemyFountain": 0, "teamBaronKills": 1, "teamDamagePercentage": 0.1982024247497744, "teamElderDragonKills": 0, "teamRiftHeraldKills": 1, "threeWardsOneSweeperCount": 0, "tookLargeDamageSurvived": 0, "turretPlatesTaken": 2, "turretTakedowns": 3, "turretsTakenWithRiftHerald": 0, "twentyMinionsIn3SecondsCount": 0, "unseenRecalls": 0, "visionScoreAdvantageLaneOpponent": 2.854341745376587, "visionScorePerMinute": 0.727887149618408, "wardTakedowns": 1, "wardTakedownsBefore20M": 0, "wardsGuarded": 0}, "champExperience": 12041, "champLevel": 14, "championId": 518, "championName": "Neeko", "championTransform": 0, "consumablesPurchased": 3, "damageDealtToBuildings": 5219, "damageDealtToObjectives": 6202, "damageDealtToTurrets": 5219, "damageSelfMitigated": 11319, "deaths": 7, "detectorWardsPlaced": 1, "doubleKills": 0, "dragonKills": 0, "eligibleForProgression": true, "firstBloodAssist": true, "firstBloodKill": false, "firstTowerAssist": false, "firstTowerKill": false, "gameEndedInEarlySurrender": false, "gameEndedInSurrender": false, "goldEarned": 9113, "goldSpent": 8125, "individualPosition": "TOP", "inhibitorKills": 1, "inhibitorTakedowns": 1, "inhibitorsLost": 0, "item0": 1056, "item1": 2420, "item2": 6656, "item3": 3020, "item4": 3115, "item5": 0, "item6": 3340, "itemsPurchased": 19, "killingSprees": 0, "kills": 3, "lane": "TOP", "largestCriticalStrike": 0, "largestKillingSpree": 0, "largestMultiKill": 1, "longestTimeSpentLiving": 406, "magicDamageDealt": 62366, "magicDamageDealtToChampions": 15526, "magicDamageTaken": 5834, "neutralMinionsKilled": 4, "nexusKills": 0, "nexusLost": 0, "nexusTakedowns": 1, "objectivesStolen": 0, "objectivesStolenAssists": 0, "participantId": 6, "pentaKills": 0, "perks": {"statPerks": {"defense": 5002, "flex": 5008, "offense": 5005}, "styles": [{"description": "primaryStyle", "selections": [{"perk": 8005, "var1": 1135, "var2": 805, "var3": 330}, {"perk": 8009, "var1": 1441, "var2": 0, "var3": 0}, {"perk": 9105, "var1": 19, "var2": 50, "var3": 0}, {"perk": 8014, "var1": 445, "var2": 0, "var3": 0}], "style": 8000}, {"description": "subStyle", "selections": [{"perk": 8105, "var1": 13, "var2": 5, "var3": 0}, {"perk": 8143, "var1": 181, "var2": 0, "var3": 0}], "style": 8100}]}, "physicalDamageDealt": 16995, "physicalDamageDealtToChampions": 3239, "physicalDamageTaken": 10219, "profileIcon": 5374, "puuid": "Up-FdUJb98DyyYRuA7H6i1nNMVNTtRDWz8kwhsHcf9VUFe-4uSBt6rA64oTSEooo-hWooGv8ji5kUg", "quadraKills": 0, "riotIdName": "", "riotIdTagline": "", "role": "SOLO", "sightWardsBoughtInGame": 0, "spell1Casts": 55, "spell2Casts": 34, "spell3Casts": 37, "spell4Casts": 10, "summoner1Casts": 5, "summoner1Id": 14, "summoner2Casts": 3, "summoner2Id": 4, "summonerId": "BD3kkFEcpr1ZF2H2JqyGqycYbEka5zN0mv7hVrV81_tmXcY", "summonerLevel": 523, "summonerName": "Govas", "teamEarlySurrendered": false, "teamId": 200, "teamPosition": "TOP", "timeCCingOthers": 37, "timePlayed": 1583, "totalDamageDealt": 88292, "totalDamageDealtToChampions": 19721, "totalDamageShieldedOnTeammates": 0, "totalDamageTaken": 17070, "totalHeal": 1356, "totalHealsOnTeammates": 0, "totalMinionsKilled": 131, "totalTimeCCDealt": 102, "totalTimeSpentDead": 212, "totalUnitsHealed": 1, "tripleKills": 0, "trueDamageDealt": 8931, "trueDamageDealtToChampions": 956, "trueDamageTaken": 1016, "turretKills": 2, "turretTakedowns": 3, "turretsLost": 2, "unrealKills": 0, "visionScore": 19, "visionWardsBoughtInGame": 1, "wardsKilled": 1, "wardsPlaced": 9, "win": true}, {"assists": 11, "baronKills": 1, "bountyLevel": 0, "challenges": {"12AssistStreakCount": 0, "abilityUses": 443, "acesBefore15Minutes": 0, "alliedJungleMonsterKills": 83.00000011920929, "baronBuffGoldAdvantageOverThreshold": 1, "baronTakedowns": 1, "blastConeOppositeOpponentCount": 0, "bountyGold": 850, "buffsStolen": 1, "completeSupportQuestInTime": 0, "controlWardTimeCoverageInRiverOrEnemyHalf": 0.7096384986376882, "controlWardsPlaced": 4, "damagePerMinute": 817.2552155953036, "damageTakenOnTeamPercentage": 0.32733857938231264, "dancedWithRiftHerald": 0, "deathsByEnemyChamps": 6, "dodgeSkillShotsSmallWindow": 1, "doubleAces": 0, "dragonTakedowns": 2, "earliestBaron": 1352.9953731933367, "earliestDragonTakedown": 596.7132881461602, "earlyLaningPhaseGoldExpAdvantage": 0, "effectiveHealAndShielding": 0, "elderDragonKillsWithOpposingSoul": 0, "elderDragonMultikills": 0, "enemyChampionImmobilizations": 20, "enemyJungleMonsterKills": 24, "epicMonsterKillsNearEnemyJungler": 0, "epicMonsterKillsWithin30SecondsOfSpawn": 1, "epicMonsterSteals": 0, "epicMonsterStolenWithoutSmite": 0, "firstTurretKilledTime": 974.2083484759784, "flawlessAces": 0, "fullTeamTakedown": 1, "gameLength": 1583.7581990769957, "goldPerMinute": 513.3751910124901, "hadOpenNexus": 0, "immobilizeAndKillWithAlly": 9, "initialBuffCount": 2, "initialCrabCount": 2, "jungleCsBefore10Minutes": 64.00000005960464, "junglerKillsEarlyJungle": 0, "junglerTakedownsNearDamagedEpicMonster": 0, "kTurretsDestroyedBeforePlatesFall": 0, "kda": 3.5, "killAfterHiddenWithAlly": 1, "killParticipation": 0.6363636363636364, "killedChampTookFullTeamDamageSurvived": 0, "killsNearEnemyTurret": 2, "killsOnLanersEarlyJungleAsJungler": 2, "killsOnRecentlyHealedByAramPack": 0, "killsUnderOwnTurret": 0, "killsWithHelpFromEpicMonster": 1, "knockEnemyIntoTeamAndKill": 0, "landSkillShotsEarlyGame": 0, "laneMinionsFirst10Minutes": 7, "laningPhaseGoldExpAdvantage": 0, "legendaryCount": 0, "lostAnInhibitor": 0, "maxCsAdvantageOnLaneOpponent": 33.79999992251396, "maxKillDeficit": 5, "maxLevelLeadLaneOpponent": 1, "moreEnemyJungleThanOpponent": -45.00000002980232, "multiKillOneSpell": 0, "multiTurretRiftHeraldCount": 0, "multikills": 1, "multikillsAfterAggressiveFlash": 0, "mythicItemUsed": 6672, "outerTurretExecutesBefore10Minutes": 0, "outnumberedKills": 2, "outnumberedNexusKill": 0, "perfectDragonSoulsTaken": 0, "perfectGame": 0, "pickKillWithAlly": 16, "poroExplosions": 0, "quickCleanse": 0, "quickFirstTurret": 0, "quickSoloKills": 0, "riftHeraldTakedowns": 1, "saveAllyFromDeath": 0, "scuttleCrabKills": 5, "shortestTimeToAceFromFirstTakedown": 22.430706622974867, "skillshotsDodged": 37, "skillshotsHit": 0, "snowballsHit": 0, "soloBaronKills": 0, "soloKills": 1, "soloTurretsLategame": 0, "stealthWardsPlaced": 2, "survivedSingleDigitHpCount": 0, "survivedThreeImmobilizesInFight": 0, "takedownOnFirstTurret": 0, "takedowns": 21, "takedownsAfterGainingLevelAdvantage": 0, "takedownsBeforeJungleMinionSpawn": 1, "takedownsFirstXMinutes": 4, "takedownsInAlcove": 0, "takedownsInEnemyFountain": 0, "teamBaronKills": 1, "teamDamagePercentage": 0.2167995455861296, "teamElderDragonKills": 0, "teamRiftHeraldKills": 1, "threeWardsOneSweeperCount": 0, "tookLargeDamageSurvived": 0, "turretPlatesTaken": 2, "turretTakedowns": 1, "turretsTakenWithRiftHerald": 0, "twentyMinionsIn3SecondsCount": 0, "unseenRecalls": 0, "visionScoreAdvantageLaneOpponent": 0.7822936773300171, "visionScorePerMinute": 1.320235910671699, "wardTakedowns": 3, "wardTakedownsBefore20M": 2, "wardsGuarded": 0}, "champExperience": 14405, "champLevel": 15, "championId": 200, "championName": "Belveth", "championTransform": 0, "consumablesPurchased": 5, "damageDealtToBuildings": 1685, "damageDealtToObjectives": 33136, "damageDealtToTurrets": 1685, "damageSelfMitigated": 32106, "deaths": 6, "detectorWardsPlaced": 4, "doubleKills": 1, "dragonKills": 2, "eligibleForProgression": true, "firstBloodAssist": true, "firstBloodKill": false, "firstTowerAssist": false, "firstTowerKill": false, "gameEndedInEarlySurrender": false, "gameEndedInSurrender": false, "goldEarned": 13551, "goldSpent": 13550, "individualPosition": "JUNGLE", "inhibitorKills": 0, "inhibitorTakedowns": 1, "inhibitorsLost": 0, "item0": 6672, "item1": 3111, "item2": 1037, "item3": 3153, "item4": 6333, "item5": 3051, "item6": 3364, "itemsPurchased": 26, "killingSprees": 3, "kills": 10, "lane": "JUNGLE", "largestCriticalStrike": 997, "largestKillingSpree": 5, "largestMultiKill": 2, "longestTimeSpentLiving": 522, "magicDamageDealt": 15362, "magicDamageDealtToChampions": 2262, "magicDamageTaken": 9994, "neutralMinionsKilled": 148, "nexusKills": 0, "nexusLost": 0, "nexusTakedowns": 0, "objectivesStolen": 0, "objectivesStolenAssists": 0, "participantId": 7, "pentaKills": 0, "perks": {"statPerks": {"defense": 5003, "flex": 5008, "offense": 5005}, "styles": [{"description": "primaryStyle", "selections": [{"perk": 8010, "var1": 679, "var2": 0, "var3": 0}, {"perk": 9111, "var1": 1218, "var2": 420, "var3": 0}, {"perk": 9104, "var1": 13, "var2": 0, "var3": 0}, {"perk": 8299, "var1": 503, "var2": 0, "var3": 0}], "style": 8000}, {"description": "subStyle", "selections": [{"perk": 8304, "var1": 9, "var2": 4, "var3": 5}, {"perk": 8347, "var1": 0, "var2": 0, "var3": 0}], "style": 8300}]}, "physicalDamageDealt": 122841, "physicalDamageDealtToChampions": 13177, "physicalDamageTaken": 19948, "profileIcon": 5290, "puuid": "-Q4TP5e0LLcrhi7jCHtIIiS5M9MnD1qnGKiRGSZuhNEJK9IJv3RbdsDtqxe1Zy-A22QbfzU7BUFWsQ", "quadraKills": 0, "riotIdName": "", "riotIdTagline": "", "role": "NONE", "sightWardsBoughtInGame": 0, "spell1Casts": 334, "spell2Casts": 58, "spell3Casts": 36, "spell4Casts": 15, "summoner1Casts": 14, "summoner1Id": 11, "summoner2Casts": 4, "summoner2Id": 4, "summonerId": "AOppEADQvhjripY2iauDm-motCTBpvW11pnFIvEqw-vooU0", "summonerLevel": 339, "summonerName": "ANGS Mocco", "teamEarlySurrendered": false, "teamId": 200, "teamPosition": "JUNGLE", "timeCCingOthers": 24, "timePlayed": 1583, "totalDamageDealt": 173583, "totalDamageDealtToChampions": 21572, "totalDamageShieldedOnTeammates": 0, "totalDamageTaken": 34190, "totalHeal": 10815, "totalHealsOnTeammates": 0, "totalMinionsKilled": 44, "totalTimeCCDealt": 324, "totalTimeSpentDead": 136, "totalUnitsHealed": 1, "tripleKills": 0, "trueDamageDealt": 35378, "trueDamageDealtToChampions": 6131, "trueDamageTaken": 4247, "turretKills": 0, "turretTakedowns": 1, "turretsLost": 2, "unrealKills": 0, "visionScore": 34, "visionWardsBoughtInGame": 5, "wardsKilled": 3, "wardsPlaced": 6, "win": true}, {"assists": 12, "baronKills": 0, "bountyLevel": 2, "challenges": {"12AssistStreakCount": 0, "abilityUses": 241, "acesBefore15Minutes": 0, "alliedJungleMonsterKills": 4.4000000059604645, "baronBuffGoldAdvantageOverThreshold": 1, "baronTakedowns": 1, "blastConeOppositeOpponentCount": 0, "bountyGold": 0, "buffsStolen": 0, "completeSupportQuestInTime": 0, "controlWardsPlaced": 0, "damagePerMinute": 1027.8380835762675, "damageTakenOnTeamPercentage": 0.18945018507478661, "dancedWithRiftHerald": 0, "deathsByEnemyChamps": 3, "dodgeSkillShotsSmallWindow": 1, "doubleAces": 0, "dragonTakedowns": 0, "earliestBaron": 1352.9953731933367, "earlyLaningPhaseGoldExpAdvantage": 0, "effectiveHealAndShielding": 0, "elderDragonKillsWithOpposingSoul": 0, "elderDragonMultikills": 0, "enemyChampionImmobilizations": 28, "enemyJungleMonsterKills": 4.000000029802322, "epicMonsterKillsNearEnemyJungler": 0, "epicMonsterKillsWithin30SecondsOfSpawn": 0, "epicMonsterSteals": 0, "epicMonsterStolenWithoutSmite": 0, "firstTurretKilledTime": 974.2083484759784, "flawlessAces": 0, "fullTeamTakedown": 1, "gameLength": 1583.7581990769957, "getTakedownsInAllLanesEarlyJungleAsLaner": 0, "goldPerMinute": 482.7931300185976, "hadOpenNexus": 0, "immobilizeAndKillWithAlly": 12, "initialBuffCount": 0, "initialCrabCount": 0, "jungleCsBefore10Minutes": 0, "junglerTakedownsNearDamagedEpicMonster": 0, "kTurretsDestroyedBeforePlatesFall": 0, "kda": 7.333333333333333, "killAfterHiddenWithAlly": 1, "killParticipation": 0.6666666666666666, "killedChampTookFullTeamDamageSurvived": 0, "killsNearEnemyTurret": 0, "killsOnOtherLanesEarlyJungleAsLaner": 0, "killsOnRecentlyHealedByAramPack": 0, "killsUnderOwnTurret": 0, "killsWithHelpFromEpicMonster": 0, "knockEnemyIntoTeamAndKill": 0, "landSkillShotsEarlyGame": 7, "laneMinionsFirst10Minutes": 69, "laningPhaseGoldExpAdvantage": 0, "legendaryCount": 0, "lostAnInhibitor": 0, "maxCsAdvantageOnLaneOpponent": 17.400000035762787, "maxKillDeficit": 5, "maxLevelLeadLaneOpponent": 2, "moreEnemyJungleThanOpponent": -109.00000008940697, "multiKillOneSpell": 1, "multiTurretRiftHeraldCount": 0, "multikills": 2, "multikillsAfterAggressiveFlash": 0, "mythicItemUsed": 6656, "outerTurretExecutesBefore10Minutes": 0, "outnumberedKills": 4, "outnumberedNexusKill": 0, "perfectDragonSoulsTaken": 0, "perfectGame": 0, "pickKillWithAlly": 16, "poroExplosions": 0, "quickCleanse": 0, "quickFirstTurret": 0, "quickSoloKills": 0, "riftHeraldTakedowns": 0, "saveAllyFromDeath": 0, "scuttleCrabKills": 0, "skillshotsDodged": 17, "skillshotsHit": 100, "snowballsHit": 0, "soloBaronKills": 0, "soloKills": 1, "soloTurretsLategame": 0, "stealthWardsPlaced": 5, "survivedSingleDigitHpCount": 0, "survivedThreeImmobilizesInFight": 0, "takedownOnFirstTurret": 0, "takedowns": 22, "takedownsAfterGainingLevelAdvantage": 1, "takedownsBeforeJungleMinionSpawn": 1, "takedownsFirstXMinutes": 5, "takedownsInAlcove": 0, "takedownsInEnemyFountain": 0, "teamBaronKills": 1, "teamDamagePercentage": 0.27266247458957615, "teamElderDragonKills": 0, "teamRiftHeraldKills": 1, "threeWardsOneSweeperCount": 0, "tookLargeDamageSurvived": 0, "turretPlatesTaken": 2, "turretTakedowns": 1, "turretsTakenWithRiftHerald": 0, "twentyMinionsIn3SecondsCount": 0, "unseenRecalls": 0, "visionScoreAdvantageLaneOpponent": -0.3472363352775574, "visionScorePerMinute": 0.3978206208761243, "wardTakedowns": 2, "wardTakedownsBefore20M": 1, "wardsGuarded": 0}, "champExperience": 14420, "champLevel": 15, "championId": 103, "championName": "Ahri", "championTransform": 0, "consumablesPurchased": 3, "damageDealtToBuildings": 2611, "damageDealtToObjectives": 7025, "damageDealtToTurrets": 2611, "damageSelfMitigated": 9816, "deaths": 3, "detectorWardsPlaced": 0, "doubleKills": 2, "dragonKills": 0, "eligibleForProgression": true, "firstBloodAssist": false, "firstBloodKill": true, "firstTowerAssist": false, "firstTowerKill": false, "gameEndedInEarlySurrender": false, "gameEndedInSurrender": false, "goldEarned": 12743, "goldSpent": 11400, "individualPosition": "MIDDLE", "inhibitorKills": 0, "inhibitorTakedowns": 0, "inhibitorsLost": 0, "item0": 3113, "item1": 6656, "item2": 3158, "item3": 3089, "item4": 3041, "item5": 3108, "item6": 3340, "itemsPurchased": 19, "killingSprees": 3, "kills": 10, "lane": "MIDDLE", "largestCriticalStrike": 0, "largestKillingSpree": 4, "largestMultiKill": 2, "longestTimeSpentLiving": 516, "magicDamageDealt": 76821, "magicDamageDealtToChampions": 18009, "magicDamageTaken": 10139, "neutralMinionsKilled": 8, "nexusKills": 0, "nexusLost": 0, "nexusTakedowns": 1, "objectivesStolen": 0, "objectivesStolenAssists": 0, "participantId": 8, "pentaKills": 0, "perks": {"statPerks": {"defense": 5003, "flex": 5008, "offense": 5005}, "styles": [{"description": "primaryStyle", "selections": [{"perk": 8112, "var1": 2003, "var2": 0, "var3": 0}, {"perk": 8139, "var1": 1022, "var2": 0, "var3": 0}, {"perk": 8138, "var1": 30, "var2": 0, "var3": 0}, {"perk": 8106, "var1": 5, "var2": 0, "var3": 0}], "style": 8100}, {"description": "subStyle", "selections": [{"perk": 8233, "var1": 14, "var2": 10, "var3": 0}, {"perk": 8236, "var1": 24, "var2": 0, "var3": 0}], "style": 8200}]}, "physicalDamageDealt": 15439, "physicalDamageDealtToChampions": 1569, "physicalDamageTaken": 7991, "profileIcon": 3186, "puuid": "w6wUMei237Ivkq7P4Htm20lrdvcbXNOXQH8ed7MHQSDZDWrRizg9PKz6-zDJX522rTY-2t0LtJMhtg", "quadraKills": 0, "riotIdName": "", "riotIdTagline": "", "role": "SOLO", "sightWardsBoughtInGame": 0, "spell1Casts": 83, "spell2Casts": 82, "spell3Casts": 38, "spell4Casts": 38, "summoner1Casts": 5, "summoner1Id": 14, "summoner2Casts": 4, "summoner2Id": 4, "summonerId": "HojockK5bZvZRydXjy87klTHSakCgYMqs1391Bs2RL_1fY4", "summonerLevel": 833, "summonerName": "Deathcounter", "teamEarlySurrendered": false, "teamId": 200, "teamPosition": "MIDDLE", "timeCCingOthers": 32, "timePlayed": 1583, "totalDamageDealt": 129986, "totalDamageDealtToChampions": 27130, "totalDamageShieldedOnTeammates": 0, "totalDamageTaken": 19788, "totalHeal": 6794, "totalHealsOnTeammates": 0, "totalMinionsKilled": 169, "totalTimeCCDealt": 101, "totalTimeSpentDead": 104, "totalUnitsHealed": 1, "tripleKills": 0, "trueDamageDealt": 37725, "trueDamageDealtToChampions": 7551, "trueDamageTaken": 1657, "turretKills": 1, "turretTakedowns": 1, "turretsLost": 2, "unrealKills": 0, "visionScore": 10, "visionWardsBoughtInGame": 0, "wardsKilled": 2, "wardsPlaced": 5, "win": true}, {"assists": 10, "baronKills": 0, "bountyLevel": 1, "challenges": {"12AssistStreakCount": 0, "abilityUses": 162, "acesBefore15Minutes": 0, "alliedJungleMonsterKills": 8.000000029802322, "baronBuffGoldAdvantageOverThreshold": 1, "baronTakedowns": 1, "blastConeOppositeOpponentCount": 0, "bountyGold": 0, "buffsStolen": 0, "completeSupportQuestInTime": 0, "controlWardTimeCoverageInRiverOrEnemyHalf": 0.16220611853651734, "controlWardsPlaced": 4, "damagePerMinute": 696.9076243493159, "damageTakenOnTeamPercentage": 0.14351863612312893, "dancedWithRiftHerald": 0, "deathsByEnemyChamps": 6, "dodgeSkillShotsSmallWindow": 0, "doubleAces": 0, "dragonTakedowns": 1, "earliestBaron": 1352.9953731933367, "earliestDragonTakedown": 916.1731442973686, "earlyLaningPhaseGoldExpAdvantage": 0, "effectiveHealAndShielding": 604, "elderDragonKillsWithOpposingSoul": 0, "elderDragonMultikills": 0, "enemyChampionImmobilizations": 0, "enemyJungleMonsterKills": 0, "epicMonsterKillsNearEnemyJungler": 0, "epicMonsterKillsWithin30SecondsOfSpawn": 0, "epicMonsterSteals": 0, "epicMonsterStolenWithoutSmite": 0, "firstTurretKilledTime": 974.2083484759784, "flawlessAces": 0, "fullTeamTakedown": 1, "gameLength": 1583.7581990769957, "getTakedownsInAllLanesEarlyJungleAsLaner": 0, "goldPerMinute": 390.8996633676795, "hadOpenNexus": 0, "immobilizeAndKillWithAlly": 0, "initialBuffCount": 0, "initialCrabCount": 0, "jungleCsBefore10Minutes": 0, "junglerTakedownsNearDamagedEpicMonster": 0, "kTurretsDestroyedBeforePlatesFall": 0, "kda": 2.5, "killAfterHiddenWithAlly": 1, "killParticipation": 0.45454545454545453, "killedChampTookFullTeamDamageSurvived": 0, "killsNearEnemyTurret": 0, "killsOnOtherLanesEarlyJungleAsLaner": 0, "killsOnRecentlyHealedByAramPack": 0, "killsUnderOwnTurret": 1, "killsWithHelpFromEpicMonster": 0, "knockEnemyIntoTeamAndKill": 0, "landSkillShotsEarlyGame": 9, "laneMinionsFirst10Minutes": 65, "laningPhaseGoldExpAdvantage": 0, "legendaryCount": 0, "lostAnInhibitor": 0, "maxCsAdvantageOnLaneOpponent": 13, "maxKillDeficit": 5, "maxLevelLeadLaneOpponent": 1, "moreEnemyJungleThanOpponent": -109.00000008940697, "multiKillOneSpell": 0, "multiTurretRiftHeraldCount": 0, "multikills": 1, "multikillsAfterAggressiveFlash": 0, "mythicItemUsed": 6692, "outerTurretExecutesBefore10Minutes": 0, "outnumberedKills": 1, "outnumberedNexusKill": 0, "perfectDragonSoulsTaken": 0, "perfectGame": 0, "pickKillWithAlly": 11, "poroExplosions": 0, "quickCleanse": 0, "quickFirstTurret": 0, "quickSoloKills": 0, "riftHeraldTakedowns": 0, "saveAllyFromDeath": 1, "scuttleCrabKills": 0, "skillshotsDodged": 9, "skillshotsHit": 115, "snowballsHit": 0, "soloBaronKills": 0, "soloKills": 1, "soloTurretsLategame": 0, "stealthWardsPlaced": 5, "survivedSingleDigitHpCount": 0, "survivedThreeImmobilizesInFight": 0, "takedownOnFirstTurret": 0, "takedowns": 15, "takedownsAfterGainingLevelAdvantage": 0, "takedownsBeforeJungleMinionSpawn": 0, "takedownsFirstXMinutes": 3, "takedownsInAlcove": 0, "takedownsInEnemyFountain": 0, "teamBaronKills": 1, "teamDamagePercentage": 0.18487401902279033, "teamElderDragonKills": 0, "teamRiftHeraldKills": 1, "threeWardsOneSweeperCount": 0, "tookLargeDamageSurvived": 0, "turretPlatesTaken": 1, "turretTakedowns": 2, "turretsTakenWithRiftHerald": 0, "twentyMinionsIn3SecondsCount": 0, "unseenRecalls": 0, "visionScoreAdvantageLaneOpponent": 1.9207334518432617, "visionScorePerMinute": 0.7462311299154951, "wardTakedowns": 2, "wardTakedownsBefore20M": 1, "wardsGuarded": 0}, "champExperience": 11124, "champLevel": 13, "championId": 21, "championName": "MissFortune", "championTransform": 0, "consumablesPurchased": 6, "damageDealtToBuildings": 5057, "damageDealtToObjectives": 8567, "damageDealtToTurrets": 5057, "damageSelfMitigated": 8863, "deaths": 6, "detectorWardsPlaced": 4, "doubleKills": 1, "dragonKills": 0, "eligibleForProgression": true, "firstBloodAssist": false, "firstBloodKill": false, "firstTowerAssist": false, "firstTowerKill": false, "gameEndedInEarlySurrender": false, "gameEndedInSurrender": false, "goldEarned": 10318, "goldSpent": 9000, "individualPosition": "BOTTOM", "inhibitorKills": 0, "inhibitorTakedowns": 0, "inhibitorsLost": 0, "item0": 6692, "item1": 3042, "item2": 3035, "item3": 0, "item4": 3047, "item5": 1036, "item6": 3363, "itemsPurchased": 26, "killingSprees": 1, "kills": 5, "lane": "BOTTOM", "largestCriticalStrike": 536, "largestKillingSpree": 3, "largestMultiKill": 2, "longestTimeSpentLiving": 532, "magicDamageDealt": 15212, "magicDamageDealtToChampions": 4063, "magicDamageTaken": 4562, "neutralMinionsKilled": 8, "nexusKills": 1, "nexusLost": 0, "nexusTakedowns": 1, "objectivesStolen": 0, "objectivesStolenAssists": 0, "participantId": 9, "pentaKills": 0, "perks": {"statPerks": {"defense": 5002, "flex": 5008, "offense": 5005}, "styles": [{"description": "primaryStyle", "selections": [{"perk": 8229, "var1": 1998, "var2": 0, "var3": 0}, {"perk": 8226, "var1": 250, "var2": 667, "var3": 0}, {"perk": 8233, "var1": 15, "var2": 0, "var3": 0}, {"perk": 8237, "var1": 585, "var2": 0, "var3": 0}], "style": 8200}, {"description": "subStyle", "selections": [{"perk": 8304, "var1": 11, "var2": 1, "var3": 5}, {"perk": 8345, "var1": 3, "var2": 0, "var3": 0}], "style": 8300}]}, "physicalDamageDealt": 69796, "physicalDamageDealtToChampions": 14331, "physicalDamageTaken": 9019, "profileIcon": 5371, "puuid": "PkM6S0PcDtaQVrFsgaUDuh42GmoX4qnot03Q66V-_mFqqVDt029bCfe4pn77tf9FhOE067gl1n0-TA", "quadraKills": 0, "riotIdName": "", "riotIdTagline": "", "role": "CARRY", "sightWardsBoughtInGame": 0, "spell1Casts": 50, "spell2Casts": 48, "spell3Casts": 54, "spell4Casts": 10, "summoner1Casts": 3, "summoner1Id": 4, "summoner2Casts": 4, "summoner2Id": 7, "summonerId": "btX11U_N7XldmMPxvQy9uijM0eUBjrygzs45Kam7WWrUME4", "summonerLevel": 270, "summonerName": "D\u0131stortion", "teamEarlySurrendered": false, "teamId": 200, "teamPosition": "BOTTOM", "timeCCingOthers": 12, "timePlayed": 1583, "totalDamageDealt": 87504, "totalDamageDealtToChampions": 18395, "totalDamageShieldedOnTeammates": 0, "totalDamageTaken": 14990, "totalHeal": 2115, "totalHealsOnTeammates": 604, "totalMinionsKilled": 142, "totalTimeCCDealt": 214, "totalTimeSpentDead": 172, "totalUnitsHealed": 4, "tripleKills": 0, "trueDamageDealt": 2495, "trueDamageDealtToChampions": 0, "trueDamageTaken": 1409, "turretKills": 0, "turretTakedowns": 2, "turretsLost": 2, "unrealKills": 0, "visionScore": 19, "visionWardsBoughtInGame": 4, "wardsKilled": 2, "wardsPlaced": 12, "win": true}, {"assists": 10, "baronKills": 0, "bountyLevel": 0, "challenges": {"12AssistStreakCount": 0, "abilityUses": 123, "acesBefore15Minutes": 0, "alliedJungleMonsterKills": 0, "baronBuffGoldAdvantageOverThreshold": 1, "baronTakedowns": 0, "blastConeOppositeOpponentCount": 0, "bountyGold": 0, "buffsStolen": 0, "completeSupportQuestInTime": 1, "controlWardTimeCoverageInRiverOrEnemyHalf": 0.2652063285201348, "controlWardsPlaced": 4, "damagePerMinute": 480.48350306472815, "damageTakenOnTeamPercentage": 0.17625964643008496, "dancedWithRiftHerald": 0, "deathsByEnemyChamps": 5, "dodgeSkillShotsSmallWindow": 1, "doubleAces": 0, "dragonTakedowns": 1, "earliestBaron": 1352.9953731933367, "earliestDragonTakedown": 916.1731442973686, "earlyLaningPhaseGoldExpAdvantage": 0, "effectiveHealAndShielding": 0, "elderDragonKillsWithOpposingSoul": 0, "elderDragonMultikills": 0, "enemyChampionImmobilizations": 21, "enemyJungleMonsterKills": 0, "epicMonsterKillsNearEnemyJungler": 0, "epicMonsterKillsWithin30SecondsOfSpawn": 0, "epicMonsterSteals": 0, "epicMonsterStolenWithoutSmite": 0, "fasterSupportQuestCompletion": 1, "firstTurretKilledTime": 974.2083484759784, "flawlessAces": 0, "fullTeamTakedown": 1, "gameLength": 1583.7581990769957, "getTakedownsInAllLanesEarlyJungleAsLaner": 0, "goldPerMinute": 350.20238490998076, "hadOpenNexus": 0, "immobilizeAndKillWithAlly": 10, "initialBuffCount": 0, "initialCrabCount": 0, "jungleCsBefore10Minutes": 0, "junglerTakedownsNearDamagedEpicMonster": 0, "kTurretsDestroyedBeforePlatesFall": 0, "kda": 3, "killAfterHiddenWithAlly": 1, "killParticipation": 0.45454545454545453, "killedChampTookFullTeamDamageSurvived": 0, "killsNearEnemyTurret": 1, "killsOnOtherLanesEarlyJungleAsLaner": 1, "killsOnRecentlyHealedByAramPack": 0, "killsUnderOwnTurret": 2, "killsWithHelpFromEpicMonster": 0, "knockEnemyIntoTeamAndKill": 0, "landSkillShotsEarlyGame": 1, "laneMinionsFirst10Minutes": 12, "laningPhaseGoldExpAdvantage": 0, "legendaryCount": 0, "lostAnInhibitor": 0, "maxCsAdvantageOnLaneOpponent": 46, "maxKillDeficit": 5, "maxLevelLeadLaneOpponent": 3, "moreEnemyJungleThanOpponent": -109.00000008940697, "multiKillOneSpell": 0, "multiTurretRiftHeraldCount": 0, "multikills": 0, "multikillsAfterAggressiveFlash": 0, "outerTurretExecutesBefore10Minutes": 0, "outnumberedKills": 0, "outnumberedNexusKill": 0, "perfectDragonSoulsTaken": 0, "perfectGame": 0, "pickKillWithAlly": 12, "poroExplosions": 0, "quickCleanse": 0, "quickFirstTurret": 0, "quickSoloKills": 0, "riftHeraldTakedowns": 1, "saveAllyFromDeath": 0, "scuttleCrabKills": 0, "shortestTimeToAceFromFirstTakedown": 22.430706622974867, "skillshotsDodged": 36, "skillshotsHit": 5, "snowballsHit": 0, "soloBaronKills": 0, "soloKills": 2, "soloTurretsLategame": 0, "stealthWardsPlaced": 16, "survivedSingleDigitHpCount": 0, "survivedThreeImmobilizesInFight": 0, "takedownOnFirstTurret": 0, "takedowns": 15, "takedownsAfterGainingLevelAdvantage": 0, "takedownsBeforeJungleMinionSpawn": 1, "takedownsFirstXMinutes": 5, "takedownsInAlcove": 1, "takedownsInEnemyFountain": 0, "teamBaronKills": 1, "teamDamagePercentage": 0.1274615360517295, "teamElderDragonKills": 0, "teamRiftHeraldKills": 1, "threeWardsOneSweeperCount": 0, "tookLargeDamageSurvived": 0, "turretPlatesTaken": 1, "turretTakedowns": 2, "turretsTakenWithRiftHerald": 0, "twentyMinionsIn3SecondsCount": 0, "unseenRecalls": 0, "visionScoreAdvantageLaneOpponent": -0.28133249282836914, "visionScorePerMinute": 1.7416235791400931, "wardTakedowns": 8, "wardTakedownsBefore20M": 4, "wardsGuarded": 0}, "champExperience": 11708, "champLevel": 14, "championId": 80, "championName": "Pantheon", "championTransform": 0, "consumablesPurchased": 11, "damageDealtToBuildings": 1745, "damageDealtToObjectives": 6663, "damageDealtToTurrets": 1745, "damageSelfMitigated": 9576, "deaths": 5, "detectorWardsPlaced": 4, "doubleKills": 0, "dragonKills": 0, "eligibleForProgression": true, "firstBloodAssist": true, "firstBloodKill": false, "firstTowerAssist": false, "firstTowerKill": false, "gameEndedInEarlySurrender": false, "gameEndedInSurrender": false, "goldEarned": 9243, "goldSpent": 9050, "individualPosition": "UTILITY", "inhibitorKills": 0, "inhibitorTakedowns": 1, "inhibitorsLost": 0, "item0": 3111, "item1": 3857, "item2": 3179, "item3": 6692, "item4": 3133, "item5": 1028, "item6": 3364, "itemsPurchased": 30, "killingSprees": 2, "kills": 5, "lane": "BOTTOM", "largestCriticalStrike": 0, "largestKillingSpree": 2, "largestMultiKill": 1, "longestTimeSpentLiving": 568, "magicDamageDealt": 2980, "magicDamageDealtToChampions": 477, "magicDamageTaken": 10153, "neutralMinionsKilled": 0, "nexusKills": 0, "nexusLost": 0, "nexusTakedowns": 0, "objectivesStolen": 0, "objectivesStolenAssists": 0, "participantId": 10, "pentaKills": 0, "perks": {"statPerks": {"defense": 5002, "flex": 5008, "offense": 5008}, "styles": [{"description": "primaryStyle", "selections": [{"perk": 8005, "var1": 1492, "var2": 781, "var3": 710}, {"perk": 9111, "var1": 808, "var2": 300, "var3": 0}, {"perk": 9105, "var1": 16, "var2": 50, "var3": 0}, {"perk": 8014, "var1": 268, "var2": 0, "var3": 0}], "style": 8000}, {"description": "subStyle", "selections": [{"perk": 8126, "var1": 659, "var2": 0, "var3": 0}, {"perk": 8105, "var1": 13, "var2": 5, "var3": 0}], "style": 8100}]}, "physicalDamageDealt": 45555, "physicalDamageDealtToChampions": 11617, "physicalDamageTaken": 6282, "profileIcon": 5012, "puuid": "APH8IvnSSc-olpTnr70_FGt-lnmL6PjeIP6S242tuRb1Py86ngS7aBDT7JNxJ0bQ56WTw3x-QjEjFQ", "quadraKills": 0, "riotIdName": "", "riotIdTagline": "", "role": "SUPPORT", "sightWardsBoughtInGame": 0, "spell1Casts": 63, "spell2Casts": 27, "spell3Casts": 28, "spell4Casts": 5, "summoner1Casts": 4, "summoner1Id": 4, "summoner2Casts": 4, "summoner2Id": 3, "summonerId": "bqemzkQBHr0haaTO1c8A4q5l_q7dADJxQfcxD6mDiB1SVgrA", "summonerLevel": 279, "summonerName": "ThadCastIe", "teamEarlySurrendered": false, "teamId": 200, "teamPosition": "UTILITY", "timeCCingOthers": 20, "timePlayed": 1583, "totalDamageDealt": 58295, "totalDamageDealtToChampions": 12682, "totalDamageShieldedOnTeammates": 0, "totalDamageTaken": 18410, "totalHeal": 2276, "totalHealsOnTeammates": 0, "totalMinionsKilled": 65, "totalTimeCCDealt": 34, "totalTimeSpentDead": 108, "totalUnitsHealed": 1, "tripleKills": 0, "trueDamageDealt": 9759, "trueDamageDealtToChampions": 587, "trueDamageTaken": 1974, "turretKills": 2, "turretTakedowns": 2, "turretsLost": 2, "unrealKills": 0, "visionScore": 45, "visionWardsBoughtInGame": 4, "wardsKilled": 8, "wardsPlaced": 20, "win": true}], "platformId": "NA1", "queueId": 420, "teams": [{"bans": [{"championId": 119, "pickTurn": 1}, {"championId": 106, "pickTurn": 2}, {"championId": 517, "pickTurn": 3}, {"championId": 350, "pickTurn": 4}, {"championId": 131, "pickTurn": 5}], "objectives": {"baron": {"first": false, "kills": 0}, "champion": {"first": false, "kills": 27}, "dragon": {"first": false, "kills": 1}, "inhibitor": {"first": false, "kills": 0}, "riftHerald": {"first": false, "kills": 1}, "tower": {"first": false, "kills": 2}}, "teamId": 100, "win": false}, {"bans": [{"championId": 235, "pickTurn": 6}, {"championId": 236, "pickTurn": 7}, {"championId": 106, "pickTurn": 8}, {"championId": 112, "pickTurn": 9}, {"championId": 41, "pickTurn": 10}], "objectives": {"baron": {"first": true, "kills": 1}, "champion": {"first": true, "kills": 33}, "dragon": {"first": true, "kills": 2}, "inhibitor": {"first": true, "kills": 1}, "riftHerald": {"first": true, "kills": 1}, "tower": {"first": true, "kills": 7}}, "teamId": 200, "win": true}], "tournamentCode": ""}}