{"metadata":{"dataVersion":"2","matchId":"NA1_4283824984","participants":["Dv0FRbdGjETpGewCV6kGevLNlVVqqv3V0tJqRG7P7TC9CVB7syf5in-Hoh4HeP844ITOSPvh-lRH0A","vhOskBGH10cjaYR8ZrLIGXpXyZfR0NulT0F9PXnicS9cD2Fc-P3cnKRy4sKKeG1qD5SzGS6_gbHrIQ","BzN1fLk5kfMK8RHIb-Y7I7_xiPIuLI_fJu7cGzfF2nxyD1AYxQnCSTWgaEzQ-taOXicq2RnEzv252g","mWDlj-uC0zu9ro4ZhWsQYiO2mUJvVTx-W8De-oA50RDvJmiw0wxPrEwZz940z8Lsseq_LvCmFI4q1w","evicBQDhiLkxz3ysyB_FeZTQOG6oYtOdhQ6azJrqHFeXLfqaZhj4-2FyDz1cR_eitwtxViIR5uAeIA","ENLAX-2Q3T1WgrOREq2Vuxvvmg6CiQ0IGwyLCNu6jP52-Nmy3m-rSFJTZZVQTbfooSgiB9pzuekrdw","Bne1btAY03_PPWjTTssIBQEn2njEoYGtT_G1487V4lKMYcPl_ppDGMsR9pdoRSEBAZ2s5vgAt-02aA","2t15WNtfFE6dMrJ7wJ26PxHY6Z5pxa4kSyr94MBxw0LtuynxtIoaU16R3YIkB4G1x5ax81o3QywqwQ","n09AHR4pCB3LkDMJLWiVDh0eIFFcN98oOpVoJlW42RbJcmdltjOJzF4rA6NeMJ6UhvkWk4U1m19l0w","LtFdHX4-a5Jds973njAW3P6FSadqDKL3Jo3Jf0ZNI2r5E_euTaW7wL77ViGolVHOvicXbIFUO5XqPA"]},"info":{"gameCreation":1650520304000,"gameDuration":1496,"gameEndTimestamp":1650521866850,"gameId":4283824984,"gameMode":"CLASSIC","gameName":"teambuilder-match-4283824984","gameStartTimestamp":1650520370278,"gameType":"MATCHED_GAME","gameVersion":"12.7.433.4138","mapId":11,"participants":[{"assists":8,"baronKills":0,"bountyLevel":0,"challenges":{"12AssistStreakCount":0,"abilityUses":306,"acesBefore15Minutes":0,"alliedJungleMonsterKills":4,"baronTakedowns":1,"blastConeOppositeOpponentCount":0,"bountyGold":0,"buffsStolen":1,"completeSupportQuestInTime":0,"controlWardsPlaced":0,"damagePerMinute":1052.9465490583912,"damageTakenOnTeamPercentage":0.33417988070899957,"dancedWithRiftHerald":0,"deathsByEnemyChamps":4,"dodgeSkillShotsSmallWindow":37,"doubleAces":0,"dragonTakedowns":1,"earliestBaron":1486.152803459067,"earliestDragonTakedown":1252.3043345538704,"earlyLaningPhaseGoldExpAdvantage":0.09909951686859131,"effectiveHealAndShielding":0,"elderDragonKillsWithOpposingSoul":0,"elderDragonMultikills":0,"enemyChampionImmobilizations":11,"enemyJungleMonsterKills":9.500000029802322,"epicMonsterKillsNearEnemyJungler":0,"epicMonsterKillsWithin30SecondsOfSpawn":0,"epicMonsterSteals":0,"epicMonsterStolenWithoutSmite":0,"firstTurretKilledTime":741.2640496081408,"flawlessAces":1,"fullTeamTakedown":0,"gameLength":1496.672637819821,"getTakedownsInAllLanesEarlyJungleAsLaner":0,"goldPerMinute":607.2014115291489,"hadAfkTeammate":0,"hadOpenNexus":0,"highestChampionDamage":1,"immobilizeAndKillWithAlly":3,"initialBuffCount":0,"initialCrabCount":0,"jungleCsBefore10Minutes":0,"junglerTakedownsNearDamagedEpicMonster":1,"kTurretsDestroyedBeforePlatesFall":1,"kda":4.75,"killAfterHiddenWithAlly":0,"killParticipation":0.7037037037037037,"killedChampTookFullTeamDamageSurvived":1,"killsNearEnemyTurret":4,"killsOnOtherLanesEarlyJungleAsLaner":0,"killsOnRecentlyHealedByAramPack":0,"killsUnderOwnTurret":0,"killsWithHelpFromEpicMonster":0,"knockEnemyIntoTeamAndKill":0,"landSkillShotsEarlyGame":2,"laneMinionsFirst10Minutes":77,"laningPhaseGoldExpAdvantage":0.28635871410369873,"legendaryCount":1,"lostAnInhibitor":0,"maxCsAdvantageOnLaneOpponent":150.00000002980232,"maxKillDeficit":5,"maxLevelLeadLaneOpponent":4,"moreEnemyJungleThanOpponent":-123.00000008940697,"multiKillOneSpell":0,"multiTurretRiftHeraldCount":0,"multikills":4,"multikillsAfterAggressiveFlash":0,"mythicItemUsed":6673,"outerTurretExecutesBefore10Minutes":0,"outnumberedKills":6,"outnumberedNexusKill":0,"perfectDragonSoulsTaken":0,"perfectGame":0,"pickKillWithAlly":10,"poroExplosions":0,"quickCleanse":0,"quickFirstTurret":0,"quickSoloKills":0,"riftHeraldTakedowns":2,"saveAllyFromDeath":0,"scuttleCrabKills":2,"shortestTimeToAceFromFirstTakedown":28.913567805192542,"skillshotsDodged":13,"skillshotsHit":24,"snowballsHit":0,"soloBaronKills":0,"soloKills":5,"soloTurretsLategame":0,"stealthWardsPlaced":7,"survivedSingleDigitHpCount":0,"survivedThreeImmobilizesInFight":0,"takedownOnFirstTurret":1,"takedowns":19,"takedownsAfterGainingLevelAdvantage":0,"takedownsBeforeJungleMinionSpawn":1,"takedownsFirst25Minutes":19,"takedownsInAlcove":0,"takedownsInEnemyFountain":0,"teamBaronKills":1,"teamDamagePercentage":0.2800379259917978,"teamElderDragonKills":0,"teamRiftHeraldKills":2,"threeWardsOneSweeperCount":0,"tookLargeDamageSurvived":0,"turretPlatesTaken":5,"turretTakedowns":4,"turretsTakenWithRiftHerald":5,"twentyMinionsIn3SecondsCount":0,"unseenRecalls":0,"visionScoreAdvantageLaneOpponent":1.28201162815094,"visionScorePerMinute":0.4708600406481472,"wardTakedowns":0,"wardTakedownsBefore20M":0,"wardsGuarded":0},"champExperience":14940,"champLevel":16,"championId":39,"championName":"Irelia","championTransform":0,"consumablesPurchased":1,"damageDealtToBuildings":7111,"damageDealtToObjectives":23608,"damageDealtToTurrets":7111,"damageSelfMitigated":36465,"deaths":4,"detectorWardsPlaced":0,"doubleKills":3,"dragonKills":0,"eligibleForProgression":true,"firstBloodAssist":false,"firstBloodKill":false,"firstTowerAssist":false,"firstTowerKill":true,"gameEndedInEarlySurrender":false,"gameEndedInSurrender":true,"goldEarned":15146,"goldSpent":14250,"individualPosition":"TOP","inhibitorKills":2,"inhibitorTakedowns":2,"inhibitorsLost":0,"item0":1055,"item1":3026,"item2":3153,"item3":3047,"item4":6673,"item5":6333,"item6":3340,"itemsPurchased":16,"killingSprees":4,"kills":11,"lane":"TOP","largestCriticalStrike":501,"largestKillingSpree":5,"largestMultiKill":3,"longestTimeSpentLiving":505,"magicDamageDealt":18074,"magicDamageDealtToChampions":6270,"magicDamageTaken":9384,"neutralMinionsKilled":24,"nexusKills":0,"nexusLost":0,"nexusTakedowns":0,"objectivesStolen":0,"objectivesStolenAssists":0,"participantId":1,"pentaKills":0,"perks":{"statPerks":{"defense":5002,"flex":5008,"offense":5005},"styles":[{"description":"primaryStyle","selections":[{"perk":8010,"var1":812,"var2":0,"var3":0},{"perk":9111,"var1":1977,"var2":380,"var3":0},{"perk":9104,"var1":13,"var2":40,"var3":0},{"perk":8299,"var1":975,"var2":0,"var3":0}],"style":8000},{"description":"subStyle","selections":[{"perk":8304,"var1":9,"var2":4,"var3":5},{"perk":8345,"var1":3,"var2":0,"var3":0}],"style":8300}]},"physicalDamageDealt":153964,"physicalDamageDealtToChampions":18732,"physicalDamageTaken":20079,"profileIcon":508,"puuid":"Dv0FRbdGjETpGewCV6kGevLNlVVqqv3V0tJqRG7P7TC9CVB7syf5in-Hoh4HeP844ITOSPvh-lRH0A","quadraKills":0,"riotIdName":"","riotIdTagline":"","role":"SOLO","sightWardsBoughtInGame":0,"spell1Casts":235,"spell2Casts":17,"spell3Casts":48,"spell4Casts":6,"summoner1Casts":6,"summoner1Id":14,"summoner2Casts":4,"summoner2Id":4,"summonerId":"Tb0oJEtk-mGHC9tnMMeyiju80Y02eL6vKFyuf8n5El27tks","summonerLevel":279,"summonerName":"K4W4K1M1","teamEarlySurrendered":false,"teamId":100,"teamPosition":"TOP","timeCCingOthers":13,"timePlayed":1496,"totalDamageDealt":176784,"totalDamageDealtToChampions":26265,"totalDamageShieldedOnTeammates":0,"totalDamageTaken":32445,"totalHeal":8017,"totalHealsOnTeammates":0,"totalMinionsKilled":191,"totalTimeCCDealt":132,"totalTimeSpentDead":151,"totalUnitsHealed":1,"tripleKills":1,"trueDamageDealt":4745,"trueDamageDealtToChampions":1262,"trueDamageTaken":2981,"turretKills":3,"turretTakedowns":4,"turretsLost":1,"unrealKills":0,"visionScore":11,"visionWardsBoughtInGame":0,"wardsKilled":0,"wardsPlaced":7,"win":true},{"assists":7,"baronKills":1,"bountyLevel":0,"challenges":{"12AssistStreakCount":0,"abilityUses":234,"acesBefore15Minutes":0,"alliedJungleMonsterKills":88.00000014901161,"baronTakedowns":1,"blastConeOppositeOpponentCount":0,"bountyGold":0,"buffsStolen":1,"completeSupportQuestInTime":0,"controlWardTimeCoverageInRiverOrEnemyHalf":0.24464613485064876,"controlWardsPlaced":2,"damagePerMinute":483.5264847422976,"damageTakenOnTeamPercentage":0.24648316777968965,"dancedWithRiftHerald":0,"deathsByEnemyChamps":5,"dodgeSkillShotsSmallWindow":37,"doubleAces":0,"dragonTakedowns":2,"earliestBaron":1486.152803459067,"earliestDragonTakedown":932.9460729676385,"earlyLaningPhaseGoldExpAdvantage":-0.2004767656326294,"effectiveHealAndShielding":0,"elderDragonKillsWithOpposingSoul":0,"elderDragonMultikills":0,"enemyChampionImmobilizations":5,"enemyJungleMonsterKills":13.000000029802322,"epicMonsterKillsNearEnemyJungler":2,"epicMonsterKillsWithin30SecondsOfSpawn":2,"epicMonsterSteals":0,"epicMonsterStolenWithoutSmite":0,"firstTurretKilledTime":741.2640496081408,"flawlessAces":1,"fullTeamTakedown":0,"gameLength":1496.672637819821,"goldPerMinute":439.9655592165456,"hadAfkTeammate":0,"hadOpenNexus":0,"highestCrowdControlScore":1,"immobilizeAndKillWithAlly":2,"initialBuffCount":2,"initialCrabCount":1,"jungleCsBefore10Minutes":56.00000008940697,"junglerKillsEarlyJungle":0,"junglerTakedownsNearDamagedEpicMonster":0,"kTurretsDestroyedBeforePlatesFall":0,"kda":3,"killAfterHiddenWithAlly":3,"killParticipation":0.5555555555555556,"killedChampTookFullTeamDamageSurvived":0,"killsNearEnemyTurret":1,"killsOnLanersEarlyJungleAsJungler":0,"killsOnRecentlyHealedByAramPack":0,"killsUnderOwnTurret":1,"killsWithHelpFromEpicMonster":0,"knockEnemyIntoTeamAndKill":0,"landSkillShotsEarlyGame":6,"laneMinionsFirst10Minutes":4,"laningPhaseGoldExpAdvantage":-0.051500678062438965,"legendaryCount":1,"lostAnInhibitor":0,"maxCsAdvantageOnLaneOpponent":34.000000059604645,"maxKillDeficit":5,"maxLevelLeadLaneOpponent":2,"moreEnemyJungleThanOpponent":-67,"multiKillOneSpell":0,"multiTurretRiftHeraldCount":0,"multikills":0,"multikillsAfterAggressiveFlash":0,"mythicItemUsed":6653,"outerTurretExecutesBefore10Minutes":0,"outnumberedKills":1,"outnumberedNexusKill":0,"perfectDragonSoulsTaken":0,"perfectGame":0,"pickKillWithAlly":10,"poroExplosions":0,"quickCleanse":0,"quickFirstTurret":0,"quickSoloKills":0,"riftHeraldTakedowns":2,"saveAllyFromDeath":0,"scuttleCrabKills":1,"shortestTimeToAceFromFirstTakedown":39.00110509797241,"skillshotsDodged":12,"skillshotsHit":23,"snowballsHit":0,"soloBaronKills":0,"soloKills":0,"soloTurretsLategame":0,"stealthWardsPlaced":1,"survivedSingleDigitHpCount":0,"survivedThreeImmobilizesInFight":0,"takedownOnFirstTurret":0,"takedowns":15,"takedownsAfterGainingLevelAdvantage":0,"takedownsBeforeJungleMinionSpawn":1,"takedownsFirst25Minutes":15,"takedownsInAlcove":0,"takedownsInEnemyFountain":0,"teamBaronKills":1,"teamDamagePercentage":0.12859698725488555,"teamElderDragonKills":0,"teamRiftHeraldKills":2,"threeWardsOneSweeperCount":0,"tookLargeDamageSurvived":0,"turretPlatesTaken":3,"turretTakedowns":2,"turretsTakenWithRiftHerald":5,"twentyMinionsIn3SecondsCount":0,"unseenRecalls":0,"visionScoreAdvantageLaneOpponent":1.1550050973892212,"visionScorePerMinute":0.5681698227166322,"wardTakedowns":2,"wardTakedownsBefore20M":2,"wardsGuarded":0},"champExperience":13164,"champLevel":15,"championId":876,"championName":"Lillia","championTransform":0,"consumablesPurchased":2,"damageDealtToBuildings":2345,"damageDealtToObjectives":24942,"damageDealtToTurrets":2345,"damageSelfMitigated":10827,"deaths":5,"detectorWardsPlaced":2,"doubleKills":0,"dragonKills":2,"eligibleForProgression":true,"firstBloodAssist":false,"firstBloodKill":false,"firstTowerAssist":false,"firstTowerKill":false,"gameEndedInEarlySurrender":false,"gameEndedInSurrender":true,"goldEarned":10974,"goldSpent":10135,"individualPosition":"JUNGLE","inhibitorKills":0,"inhibitorTakedowns":0,"inhibitorsLost":0,"item0":6653,"item1":3020,"item2":4629,"item3":1011,"item4":1026,"item5":1052,"item6":3364,"itemsPurchased":21,"killingSprees":3,"kills":8,"lane":"JUNGLE","largestCriticalStrike":0,"largestKillingSpree":3,"largestMultiKill":1,"longestTimeSpentLiving":500,"magicDamageDealt":97942,"magicDamageDealtToChampions":9064,"magicDamageTaken":4649,"neutralMinionsKilled":132,"nexusKills":0,"nexusLost":0,"nexusTakedowns":0,"objectivesStolen":0,"objectivesStolenAssists":0,"participantId":2,"pentaKills":0,"perks":{"statPerks":{"defense":5002,"flex":5008,"offense":5005},"styles":[{"description":"primaryStyle","selections":[{"perk":8010,"var1":0,"var2":0,"var3":0},{"perk":8009,"var1":2012,"var2":0,"var3":0},{"perk":9105,"var1":13,"var2":30,"var3":0},{"perk":8299,"var1":388,"var2":0,"var3":0}],"style":8000},{"description":"subStyle","selections":[{"perk":8234,"var1":11927,"var2":0,"var3":0},{"perk":8232,"var1":5,"var2":20,"var3":0}],"style":8200}]},"physicalDamageDealt":15832,"physicalDamageDealtToChampions":202,"physicalDamageTaken":18524,"profileIcon":5168,"puuid":"vhOskBGH10cjaYR8ZrLIGXpXyZfR0NulT0F9PXnicS9cD2Fc-P3cnKRy4sKKeG1qD5SzGS6_gbHrIQ","quadraKills":0,"riotIdName":"","riotIdTagline":"","role":"NONE","sightWardsBoughtInGame":0,"spell1Casts":129,"spell2Casts":52,"spell3Casts":47,"spell4Casts":6,"summoner1Casts":4,"summoner1Id":4,"summoner2Casts":14,"summoner2Id":11,"summonerId":"MYjHw_x0fuoX8ey2JMA4HqKc0oVgBJV0AmQx22jKhTTQyiY","summonerLevel":487,"summonerName":"Pokitaru","teamEarlySurrendered":false,"teamId":100,"teamPosition":"JUNGLE","timeCCingOthers":14,"timePlayed":1496,"totalDamageDealt":150220,"totalDamageDealtToChampions":12061,"totalDamageShieldedOnTeammates":0,"totalDamageTaken":23930,"totalHeal":11605,"totalHealsOnTeammates":0,"totalMinionsKilled":23,"totalTimeCCDealt":280,"totalTimeSpentDead":145,"totalUnitsHealed":1,"tripleKills":0,"trueDamageDealt":36445,"trueDamageDealtToChampions":2794,"trueDamageTaken":756,"turretKills":1,"turretTakedowns":2,"turretsLost":1,"unrealKills":0,"visionScore":14,"visionWardsBoughtInGame":2,"wardsKilled":2,"wardsPlaced":3,"win":true},{"assists":9,"baronKills":0,"bountyLevel":0,"challenges":{"12AssistStreakCount":0,"abilityUses":161,"acesBefore15Minutes":0,"alliedJungleMonsterKills":1.5,"baronTakedowns":0,"blastConeOppositeOpponentCount":0,"bountyGold":0,"buffsStolen":0,"completeSupportQuestInTime":0,"controlWardTimeCoverageInRiverOrEnemyHalf":0.13606778257096072,"controlWardsPlaced":1,"damagePerMinute":1003.9820746565265,"damageTakenOnTeamPercentage":0.147967920170215,"dancedWithRiftHerald":0,"deathsByEnemyChamps":6,"dodgeSkillShotsSmallWindow":37,"doubleAces":0,"dragonTakedowns":1,"earliestBaron":1486.152803459067,"earliestDragonTakedown":616.9563225897688,"earlyLaningPhaseGoldExpAdvantage":-0.008941948413848877,"effectiveHealAndShielding":0,"elderDragonKillsWithOpposingSoul":0,"elderDragonMultikills":0,"enemyChampionImmobilizations":0,"enemyJungleMonsterKills":0,"epicMonsterKillsNearEnemyJungler":1,"epicMonsterKillsWithin30SecondsOfSpawn":0,"epicMonsterSteals":0,"epicMonsterStolenWithoutSmite":0,"firstTurretKilledTime":741.2640496081408,"flawlessAces":1,"fullTeamTakedown":0,"gameLength":1496.672637819821,"getTakedownsInAllLanesEarlyJungleAsLaner":0,"goldPerMinute":500.83323466740603,"hadAfkTeammate":0,"hadOpenNexus":0,"immobilizeAndKillWithAlly":0,"initialBuffCount":0,"initialCrabCount":0,"jungleCsBefore10Minutes":0,"junglerTakedownsNearDamagedEpicMonster":0,"kTurretsDestroyedBeforePlatesFall":0,"kda":3.1666666666666665,"killAfterHiddenWithAlly":2,"killParticipation":0.7037037037037037,"killedChampTookFullTeamDamageSurvived":0,"killsNearEnemyTurret":2,"killsOnOtherLanesEarlyJungleAsLaner":0,"killsOnRecentlyHealedByAramPack":0,"killsUnderOwnTurret":0,"killsWithHelpFromEpicMonster":0,"knockEnemyIntoTeamAndKill":0,"landSkillShotsEarlyGame":9,"laneMinionsFirst10Minutes":89,"laningPhaseGoldExpAdvantage":-0.1165129542350769,"legendaryCount":1,"lostAnInhibitor":0,"maxCsAdvantageOnLaneOpponent":54,"maxKillDeficit":5,"maxLevelLeadLaneOpponent":1,"moreEnemyJungleThanOpponent":-123.00000008940697,"multiKillOneSpell":0,"multiTurretRiftHeraldCount":0,"multikills":2,"multikillsAfterAggressiveFlash":0,"outerTurretExecutesBefore10Minutes":0,"outnumberedKills":2,"outnumberedNexusKill":0,"perfectDragonSoulsTaken":0,"perfectGame":0,"pickKillWithAlly":10,"poroExplosions":0,"quickCleanse":0,"quickFirstTurret":0,"quickSoloKills":0,"riftHeraldTakedowns":1,"saveAllyFromDeath":0,"scuttleCrabKills":0,"skillshotsDodged":20,"skillshotsHit":22,"snowballsHit":0,"soloBaronKills":0,"soloKills":2,"soloTurretsLategame":0,"stealthWardsPlaced":6,"survivedSingleDigitHpCount":0,"survivedThreeImmobilizesInFight":0,"takedownOnFirstTurret":0,"takedowns":19,"takedownsAfterGainingLevelAdvantage":0,"takedownsBeforeJungleMinionSpawn":2,"takedownsFirst25Minutes":19,"takedownsInAlcove":0,"takedownsInEnemyFountain":0,"teamBaronKills":1,"teamDamagePercentage":0.2670155082147143,"teamElderDragonKills":0,"teamRiftHeraldKills":2,"threeWardsOneSweeperCount":0,"tookLargeDamageSurvived":0,"turretPlatesTaken":0,"turretTakedowns":4,"turretsTakenWithRiftHerald":5,"twentyMinionsIn3SecondsCount":0,"unseenRecalls":0,"visionScoreAdvantageLaneOpponent":2.107436180114746,"visionScorePerMinute":0.49587253275681314,"wardTakedowns":0,"wardTakedownsBefore20M":0,"wardsGuarded":0},"champExperience":12573,"champLevel":14,"championId":145,"championName":"Kaisa","championTransform":0,"consumablesPurchased":3,"damageDealtToBuildings":2512,"damageDealtToObjectives":4907,"damageDealtToTurrets":2512,"damageSelfMitigated":7572,"deaths":6,"detectorWardsPlaced":1,"doubleKills":2,"dragonKills":1,"eligibleForProgression":true,"firstBloodAssist":false,"firstBloodKill":false,"firstTowerAssist":false,"firstTowerKill":false,"gameEndedInEarlySurrender":false,"gameEndedInSurrender":true,"goldEarned":12493,"goldSpent":11150,"individualPosition":"MIDDLE","inhibitorKills":0,"inhibitorTakedowns":0,"inhibitorsLost":0,"item0":2055,"item1":3115,"item2":3020,"item3":6655,"item4":3145,"item5":3004,"item6":3340,"itemsPurchased":19,"killingSprees":1,"kills":10,"lane":"MIDDLE","largestCriticalStrike":0,"largestKillingSpree":7,"largestMultiKill":2,"longestTimeSpentLiving":672,"magicDamageDealt":35512,"magicDamageDealtToChampions":18115,"magicDamageTaken":8165,"neutralMinionsKilled":6,"nexusKills":0,"nexusLost":0,"nexusTakedowns":0,"objectivesStolen":0,"objectivesStolenAssists":0,"participantId":3,"pentaKills":0,"perks":{"statPerks":{"defense":5003,"flex":5008,"offense":5005},"styles":[{"description":"primaryStyle","selections":[{"perk":9923,"var1":44,"var2":73,"var3":0},{"perk":8139,"var1":991,"var2":0,"var3":0},{"perk":8138,"var1":30,"var2":0,"var3":0},{"perk":8135,"var1":400,"var2":5,"var3":0}],"style":8100},{"description":"subStyle","selections":[{"perk":8304,"var1":9,"var2":4,"var3":5},{"perk":8345,"var1":3,"var2":0,"var3":0}],"style":8300}]},"physicalDamageDealt":54590,"physicalDamageDealtToChampions":6324,"physicalDamageTaken":6048,"profileIcon":512,"puuid":"BzN1fLk5kfMK8RHIb-Y7I7_xiPIuLI_fJu7cGzfF2nxyD1AYxQnCSTWgaEzQ-taOXicq2RnEzv252g","quadraKills":0,"riotIdName":"","riotIdTagline":"","role":"SOLO","sightWardsBoughtInGame":0,"spell1Casts":59,"spell2Casts":56,"spell3Casts":38,"spell4Casts":8,"summoner1Casts":1,"summoner1Id":4,"summoner2Casts":4,"summoner2Id":14,"summonerId":"5Ou0MQ290uxpdG0E3g2qcUtDvCnsW1AmAoylUNjFaAYtBSs","summonerLevel":272,"summonerName":"Hadoku","teamEarlySurrendered":false,"teamId":100,"teamPosition":"MIDDLE","timeCCingOthers":1,"timePlayed":1496,"totalDamageDealt":90706,"totalDamageDealtToChampions":25043,"totalDamageShieldedOnTeammates":0,"totalDamageTaken":14365,"totalHeal":896,"totalHealsOnTeammates":0,"totalMinionsKilled":145,"totalTimeCCDealt":6,"totalTimeSpentDead":189,"totalUnitsHealed":1,"tripleKills":0,"trueDamageDealt":604,"trueDamageDealtToChampions":604,"trueDamageTaken":152,"turretKills":1,"turretTakedowns":4,"turretsLost":1,"unrealKills":0,"visionScore":12,"visionWardsBoughtInGame":2,"wardsKilled":0,"wardsPlaced":7,"win":true},{"assists":9,"baronKills":0,"bountyLevel":0,"challenges":{"12AssistStreakCount":0,"abilityUses":105,"acesBefore15Minutes":0,"alliedJungleMonsterKills":4.000000029802322,"baronTakedowns":0,"blastConeOppositeOpponentCount":0,"bountyGold":0,"buffsStolen":1,"completeSupportQuestInTime":0,"controlWardTimeCoverageInRiverOrEnemyHalf":0.4194239374766342,"controlWardsPlaced":2,"damagePerMinute":621.9751206832158,"damageTakenOnTeamPercentage":0.14507062914461633,"dancedWithRiftHerald":0,"deathsByEnemyChamps":5,"dodgeSkillShotsSmallWindow":37,"doubleAces":0,"dragonTakedowns":1,"earliestBaron":1486.152803459067,"earliestDragonTakedown":1252.3043345538704,"earlyLaningPhaseGoldExpAdvantage":-0.3080100417137146,"effectiveHealAndShielding":519.3154296875,"elderDragonKillsWithOpposingSoul":0,"elderDragonMultikills":0,"enemyChampionImmobilizations":12,"enemyJungleMonsterKills":4,"epicMonsterKillsNearEnemyJungler":0,"epicMonsterKillsWithin30SecondsOfSpawn":0,"epicMonsterSteals":0,"epicMonsterStolenWithoutSmite":0,"firstTurretKilledTime":741.2640496081408,"flawlessAces":1,"fullTeamTakedown":0,"gameLength":1496.672637819821,"getTakedownsInAllLanesEarlyJungleAsLaner":0,"goldPerMinute":464.285248346609,"hadAfkTeammate":0,"hadOpenNexus":0,"immobilizeAndKillWithAlly":5,"initialBuffCount":0,"initialCrabCount":0,"jungleCsBefore10Minutes":0,"junglerTakedownsNearDamagedEpicMonster":0,"kTurretsDestroyedBeforePlatesFall":0,"kda":3.2,"killAfterHiddenWithAlly":0,"killParticipation":0.5925925925925926,"killedChampTookFullTeamDamageSurvived":0,"killsNearEnemyTurret":0,"killsOnOtherLanesEarlyJungleAsLaner":0,"killsOnRecentlyHealedByAramPack":0,"killsUnderOwnTurret":0,"killsWithHelpFromEpicMonster":0,"knockEnemyIntoTeamAndKill":5,"landSkillShotsEarlyGame":9,"laneMinionsFirst10Minutes":59,"laningPhaseGoldExpAdvantage":-0.04818040132522583,"legendaryCount":0,"lostAnInhibitor":0,"maxCsAdvantageOnLaneOpponent":22,"maxKillDeficit":5,"maxLevelLeadLaneOpponent":3,"moreEnemyJungleThanOpponent":-123.00000008940697,"multiKillOneSpell":0,"multiTurretRiftHeraldCount":0,"multikills":1,"multikillsAfterAggressiveFlash":0,"mythicItemUsed":6673,"outerTurretExecutesBefore10Minutes":0,"outnumberedKills":2,"outnumberedNexusKill":0,"perfectDragonSoulsTaken":0,"perfectGame":0,"pickKillWithAlly":12,"poroExplosions":0,"quickCleanse":0,"quickFirstTurret":0,"quickSoloKills":0,"riftHeraldTakedowns":0,"saveAllyFromDeath":0,"scuttleCrabKills":0,"skillshotsDodged":30,"skillshotsHit":16,"snowballsHit":0,"soloBaronKills":0,"soloKills":0,"soloTurretsLategame":0,"stealthWardsPlaced":4,"survivedSingleDigitHpCount":0,"survivedThreeImmobilizesInFight":0,"takedownOnFirstTurret":0,"takedowns":16,"takedownsAfterGainingLevelAdvantage":0,"takedownsBeforeJungleMinionSpawn":0,"takedownsFirst25Minutes":16,"takedownsInAlcove":0,"takedownsInEnemyFountain":0,"teamBaronKills":1,"teamDamagePercentage":0.16541829494610638,"teamElderDragonKills":0,"teamRiftHeraldKills":2,"threeWardsOneSweeperCount":0,"tookLargeDamageSurvived":0,"turretPlatesTaken":1,"turretTakedowns":6,"turretsTakenWithRiftHerald":5,"twentyMinionsIn3SecondsCount":0,"unseenRecalls":0,"visionScoreAdvantageLaneOpponent":5.396550178527832,"visionScorePerMinute":1.1937390047629373,"wardTakedowns":1,"wardTakedownsBefore20M":0,"wardsGuarded":0},"champExperience":11975,"champLevel":14,"championId":67,"championName":"Vayne","championTransform":0,"consumablesPurchased":9,"damageDealtToBuildings":6717,"damageDealtToObjectives":12461,"damageDealtToTurrets":6717,"damageSelfMitigated":7217,"deaths":5,"detectorWardsPlaced":2,"doubleKills":1,"dragonKills":0,"eligibleForProgression":true,"firstBloodAssist":false,"firstBloodKill":false,"firstTowerAssist":false,"firstTowerKill":false,"gameEndedInEarlySurrender":false,"gameEndedInSurrender":true,"goldEarned":11581,"goldSpent":11175,"individualPosition":"BOTTOM","inhibitorKills":0,"inhibitorTakedowns":2,"inhibitorsLost":0,"item0":6673,"item1":2055,"item2":3006,"item3":3091,"item4":3124,"item5":0,"item6":3363,"itemsPurchased":27,"killingSprees":3,"kills":7,"lane":"BOTTOM","largestCriticalStrike":0,"largestKillingSpree":3,"largestMultiKill":2,"longestTimeSpentLiving":476,"magicDamageDealt":1245,"magicDamageDealtToChampions":0,"magicDamageTaken":6602,"neutralMinionsKilled":8,"nexusKills":0,"nexusLost":0,"nexusTakedowns":0,"objectivesStolen":0,"objectivesStolenAssists":0,"participantId":4,"pentaKills":0,"perks":{"statPerks":{"defense":5002,"flex":5008,"offense":5005},"styles":[{"description":"primaryStyle","selections":[{"perk":8008,"var1":49,"var2":2,"var3":0},{"perk":9111,"var1":460,"var2":320,"var3":0},{"perk":9104,"var1":17,"var2":0,"var3":0},{"perk":8014,"var1":377,"var2":0,"var3":0}],"style":8000},{"description":"subStyle","selections":[{"perk":8139,"var1":631,"var2":0,"var3":0},{"perk":8135,"var1":400,"var2":5,"var3":0}],"style":8100}]},"physicalDamageDealt":71306,"physicalDamageDealtToChampions":10628,"physicalDamageTaken":6844,"profileIcon":583,"puuid":"mWDlj-uC0zu9ro4ZhWsQYiO2mUJvVTx-W8De-oA50RDvJmiw0wxPrEwZz940z8Lsseq_LvCmFI4q1w","quadraKills":0,"riotIdName":"","riotIdTagline":"","role":"CARRY","sightWardsBoughtInGame":0,"spell1Casts":91,"spell2Casts":0,"spell3Casts":9,"spell4Casts":5,"summoner1Casts":5,"summoner1Id":7,"summoner2Casts":5,"summoner2Id":4,"summonerId":"R_B3bLtTyI6smUU3_2bgNxW5FTTZn_rfbCSKe9PvrGYABJY","summonerLevel":230,"summonerName":"Teddee","teamEarlySurrendered":false,"teamId":100,"teamPosition":"BOTTOM","timeCCingOthers":9,"timePlayed":1496,"totalDamageDealt":84517,"totalDamageDealtToChampions":15514,"totalDamageShieldedOnTeammates":0,"totalDamageTaken":14084,"totalHeal":2030,"totalHealsOnTeammates":519,"totalMinionsKilled":133,"totalTimeCCDealt":34,"totalTimeSpentDead":127,"totalUnitsHealed":2,"tripleKills":0,"trueDamageDealt":11965,"trueDamageDealtToChampions":4886,"trueDamageTaken":637,"turretKills":5,"turretTakedowns":6,"turretsLost":1,"unrealKills":0,"visionScore":29,"visionWardsBoughtInGame":3,"wardsKilled":1,"wardsPlaced":8,"win":true},{"assists":12,"baronKills":0,"bountyLevel":0,"challenges":{"12AssistStreakCount":0,"abilityUses":218,"acesBefore15Minutes":0,"alliedJungleMonsterKills":0,"baronTakedowns":1,"blastConeOppositeOpponentCount":0,"bountyGold":150,"buffsStolen":0,"completeSupportQuestInTime":1,"controlWardTimeCoverageInRiverOrEnemyHalf":0.28440726745997297,"controlWardsPlaced":4,"damagePerMinute":597.5838665547062,"damageTakenOnTeamPercentage":0.12629840219647942,"dancedWithRiftHerald":0,"deathsByEnemyChamps":7,"dodgeSkillShotsSmallWindow":37,"doubleAces":0,"dragonTakedowns":1,"earliestBaron":1486.152803459067,"earliestDragonTakedown":616.9563225897688,"earlyLaningPhaseGoldExpAdvantage":-0.11614888906478882,"effectiveHealAndShielding":695.8973388671875,"elderDragonKillsWithOpposingSoul":0,"elderDragonMultikills":0,"enemyChampionImmobilizations":14,"enemyJungleMonsterKills":0,"epicMonsterKillsNearEnemyJungler":0,"epicMonsterKillsWithin30SecondsOfSpawn":0,"epicMonsterSteals":0,"epicMonsterStolenWithoutSmite":0,"firstTurretKilledTime":741.2640496081408,"flawlessAces":1,"fullTeamTakedown":0,"gameLength":1496.672637819821,"getTakedownsInAllLanesEarlyJungleAsLaner":0,"goldPerMinute":384.30408080527326,"hadAfkTeammate":0,"hadOpenNexus":0,"highestWardKills":1,"immobilizeAndKillWithAlly":6,"initialBuffCount":0,"initialCrabCount":0,"jungleCsBefore10Minutes":0,"junglerTakedownsNearDamagedEpicMonster":1,"kTurretsDestroyedBeforePlatesFall":0,"kda":2.2857142857142856,"killAfterHiddenWithAlly":1,"killParticipation":0.5925925925925926,"killedChampTookFullTeamDamageSurvived":1,"killsNearEnemyTurret":0,"killsOnOtherLanesEarlyJungleAsLaner":0,"killsOnRecentlyHealedByAramPack":0,"killsUnderOwnTurret":1,"killsWithHelpFromEpicMonster":0,"knockEnemyIntoTeamAndKill":0,"landSkillShotsEarlyGame":5,"laneMinionsFirst10Minutes":15,"laningPhaseGoldExpAdvantage":-0.11697310209274292,"legendaryCount":0,"lostAnInhibitor":0,"maxCsAdvantageOnLaneOpponent":17,"maxKillDeficit":5,"maxLevelLeadLaneOpponent":1,"moreEnemyJungleThanOpponent":-123.00000008940697,"multiKillOneSpell":0,"multiTurretRiftHeraldCount":0,"multikills":0,"multikillsAfterAggressiveFlash":0,"mythicItemUsed":4644,"outerTurretExecutesBefore10Minutes":0,"outnumberedKills":2,"outnumberedNexusKill":0,"perfectDragonSoulsTaken":0,"perfectGame":0,"pickKillWithAlly":12,"poroExplosions":0,"quickCleanse":0,"quickFirstTurret":0,"quickSoloKills":0,"riftHeraldTakedowns":0,"saveAllyFromDeath":0,"scuttleCrabKills":0,"skillshotsDodged":33,"skillshotsHit":28,"snowballsHit":0,"soloBaronKills":0,"soloKills":1,"soloTurretsLategame":0,"stealthWardsPlaced":10,"survivedSingleDigitHpCount":0,"survivedThreeImmobilizesInFight":0,"takedownOnFirstTurret":0,"takedowns":16,"takedownsAfterGainingLevelAdvantage":0,"takedownsBeforeJungleMinionSpawn":1,"takedownsFirst25Minutes":16,"takedownsInAlcove":0,"takedownsInEnemyFountain":0,"teamBaronKills":1,"teamDamagePercentage":0.15893128359249598,"teamElderDragonKills":0,"teamRiftHeraldKills":2,"threeWardsOneSweeperCount":0,"tookLargeDamageSurvived":0,"turretPlatesTaken":0,"turretTakedowns":3,"turretsTakenWithRiftHerald":5,"twentyMinionsIn3SecondsCount":0,"unseenRecalls":0,"visionScoreAdvantageLaneOpponent":1.4009594917297363,"visionScorePerMinute":1.3569922225817843,"wardTakedowns":4,"wardTakedownsBefore20M":4,"wardsGuarded":0},"champExperience":10627,"champLevel":13,"championId":99,"championName":"Lux","championTransform":0,"consumablesPurchased":7,"damageDealtToBuildings":2900,"damageDealtToObjectives":3833,"damageDealtToTurrets":2900,"damageSelfMitigated":6540,"deaths":7,"detectorWardsPlaced":4,"doubleKills":0,"dragonKills":0,"eligibleForProgression":true,"firstBloodAssist":false,"firstBloodKill":false,"firstTowerAssist":false,"firstTowerKill":false,"gameEndedInEarlySurrender":false,"gameEndedInSurrender":true,"goldEarned":9586,"goldSpent":8975,"individualPosition":"UTILITY","inhibitorKills":0,"inhibitorTakedowns":0,"inhibitorsLost":0,"item0":4644,"item1":3020,"item2":3041,"item3":3853,"item4":3157,"item5":2055,"item6":3364,"itemsPurchased":24,"killingSprees":0,"kills":4,"lane":"BOTTOM","largestCriticalStrike":0,"largestKillingSpree":0,"largestMultiKill":1,"longestTimeSpentLiving":308,"magicDamageDealt":47246,"magicDamageDealtToChampions":13436,"magicDamageTaken":4904,"neutralMinionsKilled":0,"nexusKills":0,"nexusLost":0,"nexusTakedowns":0,"objectivesStolen":0,"objectivesStolenAssists":0,"participantId":5,"pentaKills":0,"perks":{"statPerks":{"defense":5001,"flex":5008,"offense":5008},"styles":[{"description":"primaryStyle","selections":[{"perk":8229,"var1":1547,"var2":0,"var3":0},{"perk":8226,"var1":250,"var2":802,"var3":0},{"perk":8233,"var1":16,"var2":40,"var3":0},{"perk":8237,"var1":491,"var2":0,"var3":0}],"style":8200},{"description":"subStyle","selections":[{"perk":8126,"var1":598,"var2":0,"var3":0},{"perk":8135,"var1":400,"var2":5,"var3":0}],"style":8100}]},"physicalDamageDealt":4036,"physicalDamageDealtToChampions":729,"physicalDamageTaken":7005,"profileIcon":1381,"puuid":"evicBQDhiLkxz3ysyB_FeZTQOG6oYtOdhQ6azJrqHFeXLfqaZhj4-2FyDz1cR_eitwtxViIR5uAeIA","quadraKills":0,"riotIdName":"","riotIdTagline":"","role":"SUPPORT","sightWardsBoughtInGame":0,"spell1Casts":47,"spell2Casts":21,"spell3Casts":139,"spell4Casts":11,"summoner1Casts":2,"summoner1Id":14,"summoner2Casts":4,"summoner2Id":4,"summonerId":"A5HzLQb7OVF8pKP3ExqaEm6BUmshvNRz89bAHQTwPf-874Q","summonerLevel":222,"summonerName":"Octobr","teamEarlySurrendered":false,"teamId":100,"teamPosition":"UTILITY","timeCCingOthers":31,"timePlayed":1496,"totalDamageDealt":52162,"totalDamageDealtToChampions":14906,"totalDamageShieldedOnTeammates":695,"totalDamageTaken":12262,"totalHeal":0,"totalHealsOnTeammates":0,"totalMinionsKilled":49,"totalTimeCCDealt":236,"totalTimeSpentDead":161,"totalUnitsHealed":0,"tripleKills":0,"trueDamageDealt":878,"trueDamageDealtToChampions":740,"trueDamageTaken":351,"turretKills":0,"turretTakedowns":3,"turretsLost":1,"unrealKills":0,"visionScore":33,"visionWardsBoughtInGame":5,"wardsKilled":4,"wardsPlaced":14,"win":true},{"assists":5,"baronKills":0,"bountyLevel":0,"challenges":{"12AssistStreakCount":0,"abilityUses":139,"acesBefore15Minutes":0,"alliedJungleMonsterKills":0,"baronTakedowns":0,"blastConeOppositeOpponentCount":0,"bountyGold":300,"buffsStolen":0,"completeSupportQuestInTime":0,"controlWardsPlaced":0,"damagePerMinute":500.2557427133144,"damageTakenOnTeamPercentage":0.21031483525944375,"dancedWithRiftHerald":0,"deathsByEnemyChamps":9,"dodgeSkillShotsSmallWindow":37,"doubleAces":0,"dragonTakedowns":0,"earlyLaningPhaseGoldExpAdvantage":-0.2752123475074768,"effectiveHealAndShielding":0,"elderDragonKillsWithOpposingSoul":0,"elderDragonMultikills":0,"enemyChampionImmobilizations":6,"enemyJungleMonsterKills":0,"epicMonsterKillsNearEnemyJungler":0,"epicMonsterKillsWithin30SecondsOfSpawn":0,"epicMonsterSteals":0,"epicMonsterStolenWithoutSmite":0,"flawlessAces":0,"fullTeamTakedown":2,"gameLength":1496.672637819821,"getTakedownsInAllLanesEarlyJungleAsLaner":0,"goldPerMinute":302.98345765297626,"hadAfkTeammate":0,"hadOpenNexus":0,"immobilizeAndKillWithAlly":1,"initialBuffCount":0,"initialCrabCount":0,"jungleCsBefore10Minutes":0,"junglerTakedownsNearDamagedEpicMonster":0,"kTurretsDestroyedBeforePlatesFall":0,"kda":0.8888888888888888,"killAfterHiddenWithAlly":1,"killParticipation":0.2,"killedChampTookFullTeamDamageSurvived":0,"killsNearEnemyTurret":0,"killsOnOtherLanesEarlyJungleAsLaner":0,"killsOnRecentlyHealedByAramPack":0,"killsUnderOwnTurret":1,"killsWithHelpFromEpicMonster":0,"knockEnemyIntoTeamAndKill":0,"landSkillShotsEarlyGame":2,"laneMinionsFirst10Minutes":32,"laningPhaseGoldExpAdvantage":-0.38842010498046875,"legendaryCount":0,"lostAnInhibitor":0,"maxCsAdvantageOnLaneOpponent":2,"maxKillDeficit":0,"maxLevelLeadLaneOpponent":1,"moreEnemyJungleThanOpponent":-123.00000008940697,"multiKillOneSpell":0,"multiTurretRiftHeraldCount":0,"multikills":0,"multikillsAfterAggressiveFlash":0,"outerTurretExecutesBefore10Minutes":0,"outnumberedKills":0,"outnumberedNexusKill":0,"perfectDragonSoulsTaken":0,"perfectGame":0,"pickKillWithAlly":7,"poroExplosions":0,"quickCleanse":0,"quickFirstTurret":0,"quickSoloKills":0,"riftHeraldTakedowns":0,"saveAllyFromDeath":0,"scuttleCrabKills":0,"skillshotsDodged":55,"skillshotsHit":20,"snowballsHit":0,"soloBaronKills":0,"soloKills":0,"soloTurretsLategame":0,"stealthWardsPlaced":6,"survivedSingleDigitHpCount":0,"survivedThreeImmobilizesInFight":0,"takedownOnFirstTurret":0,"takedowns":8,"takedownsAfterGainingLevelAdvantage":0,"takedownsBeforeJungleMinionSpawn":2,"takedownsFirst25Minutes":8,"takedownsInAlcove":0,"takedownsInEnemyFountain":0,"teamBaronKills":0,"teamDamagePercentage":0.19164827270211676,"teamElderDragonKills":0,"teamRiftHeraldKills":0,"threeWardsOneSweeperCount":0,"tookLargeDamageSurvived":0,"turretPlatesTaken":3,"turretTakedowns":0,"turretsTakenWithRiftHerald":0,"twentyMinionsIn3SecondsCount":0,"unseenRecalls":0,"visionScoreAdvantageLaneOpponent":0.7800241112709045,"visionScorePerMinute":0.3672821964844703,"wardTakedowns":1,"wardTakedownsBefore20M":1,"wardsGuarded":0},"champExperience":10399,"champLevel":13,"championId":83,"championName":"Yorick","championTransform":0,"consumablesPurchased":1,"damageDealtToBuildings":2429,"damageDealtToObjectives":2518,"damageDealtToTurrets":2429,"damageSelfMitigated":16215,"deaths":9,"detectorWardsPlaced":0,"doubleKills":0,"dragonKills":0,"eligibleForProgression":true,"firstBloodAssist":false,"firstBloodKill":true,"firstTowerAssist":false,"firstTowerKill":false,"gameEndedInEarlySurrender":false,"gameEndedInSurrender":true,"goldEarned":7557,"goldSpent":6900,"individualPosition":"TOP","inhibitorKills":0,"inhibitorTakedowns":0,"inhibitorsLost":2,"item0":3181,"item1":1054,"item2":3047,"item3":3057,"item4":3067,"item5":3051,"item6":3340,"itemsPurchased":13,"killingSprees":0,"kills":3,"lane":"TOP","largestCriticalStrike":0,"largestKillingSpree":0,"largestMultiKill":1,"longestTimeSpentLiving":413,"magicDamageDealt":12956,"magicDamageDealtToChampions":4638,"magicDamageTaken":6833,"neutralMinionsKilled":0,"nexusKills":0,"nexusLost":0,"nexusTakedowns":0,"objectivesStolen":0,"objectivesStolenAssists":0,"participantId":6,"pentaKills":0,"perks":{"statPerks":{"defense":5002,"flex":5008,"offense":5008},"styles":[{"description":"primaryStyle","selections":[{"perk":8437,"var1":673,"var2":483,"var3":0},{"perk":8446,"var1":511,"var2":0,"var3":0},{"perk":8473,"var1":969,"var2":0,"var3":0},{"perk":8451,"var1":181,"var2":0,"var3":0}],"style":8400},{"description":"subStyle","selections":[{"perk":8009,"var1":1264,"var2":0,"var3":0},{"perk":8014,"var1":153,"var2":0,"var3":0}],"style":8000}]},"physicalDamageDealt":45015,"physicalDamageDealtToChampions":7797,"physicalDamageTaken":13240,"profileIcon":27,"puuid":"ENLAX-2Q3T1WgrOREq2Vuxvvmg6CiQ0IGwyLCNu6jP52-Nmy3m-rSFJTZZVQTbfooSgiB9pzuekrdw","quadraKills":0,"riotIdName":"","riotIdTagline":"","role":"SOLO","sightWardsBoughtInGame":0,"spell1Casts":78,"spell2Casts":22,"spell3Casts":34,"spell4Casts":5,"summoner1Casts":0,"summoner1Id":14,"summoner2Casts":2,"summoner2Id":12,"summonerId":"mIxLuf3Fln8r70BXcDhuQhB4KrpU3RuK7Gi6aIkhhS3SY8Eg","summonerLevel":68,"summonerName":"papa6less","teamEarlySurrendered":false,"teamId":200,"teamPosition":"TOP","timeCCingOthers":5,"timePlayed":1496,"totalDamageDealt":62250,"totalDamageDealtToChampions":12478,"totalDamageShieldedOnTeammates":0,"totalDamageTaken":23226,"totalHeal":2473,"totalHealsOnTeammates":0,"totalMinionsKilled":70,"totalTimeCCDealt":87,"totalTimeSpentDead":265,"totalUnitsHealed":1,"tripleKills":0,"trueDamageDealt":4278,"trueDamageDealtToChampions":42,"trueDamageTaken":3152,"turretKills":0,"turretTakedowns":0,"turretsLost":10,"unrealKills":0,"visionScore":9,"visionWardsBoughtInGame":0,"wardsKilled":1,"wardsPlaced":6,"win":false},{"assists":6,"baronKills":0,"bountyLevel":0,"challenges":{"12AssistStreakCount":0,"abilityUses":242,"acesBefore15Minutes":0,"alliedJungleMonsterKills":83.50000014901161,"baronTakedowns":0,"blastConeOppositeOpponentCount":0,"bountyGold":150,"buffsStolen":0,"completeSupportQuestInTime":0,"controlWardTimeCoverageInRiverOrEnemyHalf":0.17627959765443277,"controlWardsPlaced":3,"damagePerMinute":564.2281176372466,"damageTakenOnTeamPercentage":0.21877056400718123,"dancedWithRiftHerald":0,"deathsByEnemyChamps":8,"dodgeSkillShotsSmallWindow":37,"doubleAces":0,"dragonTakedowns":1,"earliestDragonTakedown":616.9563225897688,"earlyLaningPhaseGoldExpAdvantage":0.22082626819610596,"effectiveHealAndShielding":0,"elderDragonKillsWithOpposingSoul":0,"elderDragonMultikills":0,"enemyChampionImmobilizations":0,"enemyJungleMonsterKills":0,"epicMonsterKillsNearEnemyJungler":0,"epicMonsterKillsWithin30SecondsOfSpawn":0,"epicMonsterSteals":0,"epicMonsterStolenWithoutSmite":0,"flawlessAces":0,"fullTeamTakedown":2,"gameLength":1496.672637819821,"goldPerMinute":391.61369372916977,"hadAfkTeammate":0,"hadOpenNexus":0,"immobilizeAndKillWithAlly":0,"initialBuffCount":2,"initialCrabCount":1,"jungleCsBefore10Minutes":56.00000008940697,"junglerKillsEarlyJungle":1,"junglerTakedownsNearDamagedEpicMonster":0,"kTurretsDestroyedBeforePlatesFall":0,"kda":1.625,"killAfterHiddenWithAlly":1,"killParticipation":0.325,"killedChampTookFullTeamDamageSurvived":0,"killsNearEnemyTurret":1,"killsOnLanersEarlyJungleAsJungler":0,"killsOnRecentlyHealedByAramPack":0,"killsUnderOwnTurret":0,"killsWithHelpFromEpicMonster":1,"knockEnemyIntoTeamAndKill":0,"landSkillShotsEarlyGame":6,"laneMinionsFirst10Minutes":5,"laningPhaseGoldExpAdvantage":0.0532069206237793,"legendaryCount":0,"lostAnInhibitor":0,"maxCsAdvantageOnLaneOpponent":16.000000029802322,"maxKillDeficit":0,"maxLevelLeadLaneOpponent":1,"moreEnemyJungleThanOpponent":-67,"multiKillOneSpell":0,"multiTurretRiftHeraldCount":0,"multikills":0,"multikillsAfterAggressiveFlash":0,"mythicItemUsed":6693,"outerTurretExecutesBefore10Minutes":0,"outnumberedKills":2,"outnumberedNexusKill":0,"perfectDragonSoulsTaken":0,"perfectGame":0,"pickKillWithAlly":8,"poroExplosions":0,"quickCleanse":0,"quickFirstTurret":0,"quickSoloKills":0,"riftHeraldTakedowns":0,"saveAllyFromDeath":0,"scuttleCrabKills":2,"skillshotsDodged":30,"skillshotsHit":15,"snowballsHit":0,"soloBaronKills":0,"soloKills":4,"soloTurretsLategame":0,"stealthWardsPlaced":2,"survivedSingleDigitHpCount":0,"survivedThreeImmobilizesInFight":0,"takedownOnFirstTurret":0,"takedowns":13,"takedownsAfterGainingLevelAdvantage":0,"takedownsBeforeJungleMinionSpawn":2,"takedownsFirst25Minutes":13,"takedownsInAlcove":0,"takedownsInEnemyFountain":0,"teamBaronKills":0,"teamDamagePercentage":0.21615612760114555,"teamElderDragonKills":0,"teamRiftHeraldKills":0,"threeWardsOneSweeperCount":0,"tookLargeDamageSurvived":0,"turretPlatesTaken":0,"turretTakedowns":0,"turretsTakenWithRiftHerald":0,"twentyMinionsIn3SecondsCount":0,"unseenRecalls":0,"visionScoreAdvantageLaneOpponent":0.8657970428466797,"visionScorePerMinute":0.4919197490251534,"wardTakedowns":2,"wardTakedownsBefore20M":2,"wardsGuarded":1},"champExperience":11153,"champLevel":13,"championId":141,"championName":"Kayn","championTransform":2,"consumablesPurchased":3,"damageDealtToBuildings":0,"damageDealtToObjectives":10948,"damageDealtToTurrets":0,"damageSelfMitigated":10184,"deaths":8,"detectorWardsPlaced":3,"doubleKills":0,"dragonKills":0,"eligibleForProgression":true,"firstBloodAssist":true,"firstBloodKill":false,"firstTowerAssist":false,"firstTowerKill":false,"gameEndedInEarlySurrender":false,"gameEndedInSurrender":true,"goldEarned":9768,"goldSpent":9175,"individualPosition":"JUNGLE","inhibitorKills":0,"inhibitorTakedowns":0,"inhibitorsLost":2,"item0":3042,"item1":6693,"item2":1036,"item3":3134,"item4":3158,"item5":1036,"item6":3364,"itemsPurchased":25,"killingSprees":2,"kills":7,"lane":"JUNGLE","largestCriticalStrike":0,"largestKillingSpree":2,"largestMultiKill":1,"longestTimeSpentLiving":546,"magicDamageDealt":5683,"magicDamageDealtToChampions":1264,"magicDamageTaken":9948,"neutralMinionsKilled":94,"nexusKills":0,"nexusLost":0,"nexusTakedowns":0,"objectivesStolen":0,"objectivesStolenAssists":0,"participantId":7,"pentaKills":0,"perks":{"statPerks":{"defense":5002,"flex":5008,"offense":5008},"styles":[{"description":"primaryStyle","selections":[{"perk":8369,"var1":692,"var2":697,"var3":0},{"perk":8304,"var1":9,"var2":0,"var3":0},{"perk":8321,"var1":5,"var2":0,"var3":0},{"perk":8347,"var1":0,"var2":0,"var3":0}],"style":8300},{"description":"subStyle","selections":[{"perk":8143,"var1":416,"var2":0,"var3":0},{"perk":8134,"var1":17,"var2":5,"var3":0}],"style":8100}]},"physicalDamageDealt":100416,"physicalDamageDealtToChampions":11353,"physicalDamageTaken":12005,"profileIcon":5083,"puuid":"Bne1btAY03_PPWjTTssIBQEn2njEoYGtT_G1487V4lKMYcPl_ppDGMsR9pdoRSEBAZ2s5vgAt-02aA","quadraKills":0,"riotIdName":"","riotIdTagline":"","role":"NONE","sightWardsBoughtInGame":0,"spell1Casts":110,"spell2Casts":56,"spell3Casts":60,"spell4Casts":16,"summoner1Casts":5,"summoner1Id":4,"summoner2Casts":13,"summoner2Id":11,"summonerId":"MCWhkKkd-N3L2htmOp2dzE4S9lwUIH5EK3QtoG50CXLt6kjBoPL-oX-Wmw","summonerLevel":179,"summonerName":"Thebrawler1ke","teamEarlySurrendered":false,"teamId":200,"teamPosition":"JUNGLE","timeCCingOthers":6,"timePlayed":1496,"totalDamageDealt":115988,"totalDamageDealtToChampions":14074,"totalDamageShieldedOnTeammates":0,"totalDamageTaken":24160,"totalHeal":8439,"totalHealsOnTeammates":0,"totalMinionsKilled":35,"totalTimeCCDealt":138,"totalTimeSpentDead":239,"totalUnitsHealed":1,"tripleKills":0,"trueDamageDealt":9889,"trueDamageDealtToChampions":1456,"trueDamageTaken":2206,"turretKills":0,"turretTakedowns":0,"turretsLost":10,"unrealKills":0,"visionScore":12,"visionWardsBoughtInGame":3,"wardsKilled":2,"wardsPlaced":5,"win":false},{"assists":2,"baronKills":0,"bountyLevel":0,"challenges":{"12AssistStreakCount":0,"abilityUses":165,"acesBefore15Minutes":0,"alliedJungleMonsterKills":0,"baronTakedowns":0,"blastConeOppositeOpponentCount":0,"bountyGold":1150,"buffsStolen":0,"completeSupportQuestInTime":0,"controlWardsPlaced":0,"damagePerMinute":505.21326312810487,"damageTakenOnTeamPercentage":0.1914621460974599,"dancedWithRiftHerald":0,"deathsByEnemyChamps":7,"dodgeSkillShotsSmallWindow":37,"doubleAces":0,"dragonTakedowns":0,"earlyLaningPhaseGoldExpAdvantage":-0.11489176750183105,"effectiveHealAndShielding":0,"elderDragonKillsWithOpposingSoul":0,"elderDragonMultikills":0,"enemyChampionImmobilizations":9,"enemyJungleMonsterKills":0,"epicMonsterKillsNearEnemyJungler":0,"epicMonsterKillsWithin30SecondsOfSpawn":0,"epicMonsterSteals":0,"epicMonsterStolenWithoutSmite":0,"flawlessAces":0,"fullTeamTakedown":2,"gameLength":1496.672637819821,"getTakedownsInAllLanesEarlyJungleAsLaner":0,"goldPerMinute":389.8871685669846,"hadAfkTeammate":0,"hadOpenNexus":0,"immobilizeAndKillWithAlly":5,"initialBuffCount":0,"initialCrabCount":0,"jungleCsBefore10Minutes":0,"junglerTakedownsNearDamagedEpicMonster":0,"kTurretsDestroyedBeforePlatesFall":0,"kda":1.4285714285714286,"killAfterHiddenWithAlly":2,"killParticipation":0.25,"killedChampTookFullTeamDamageSurvived":0,"killsNearEnemyTurret":0,"killsOnOtherLanesEarlyJungleAsLaner":0,"killsOnRecentlyHealedByAramPack":0,"killsUnderOwnTurret":2,"killsWithHelpFromEpicMonster":0,"knockEnemyIntoTeamAndKill":0,"landSkillShotsEarlyGame":4,"laneMinionsFirst10Minutes":54,"laningPhaseGoldExpAdvantage":-0.08779656887054443,"legendaryCount":1,"lostAnInhibitor":0,"maxCsAdvantageOnLaneOpponent":0,"maxKillDeficit":0,"maxLevelLeadLaneOpponent":1,"moreEnemyJungleThanOpponent":-123.00000008940697,"multiKillOneSpell":0,"multiTurretRiftHeraldCount":0,"multikills":0,"multikillsAfterAggressiveFlash":0,"mythicItemUsed":6656,"outerTurretExecutesBefore10Minutes":0,"outnumberedKills":3,"outnumberedNexusKill":0,"perfectDragonSoulsTaken":0,"perfectGame":0,"pickKillWithAlly":6,"poroExplosions":0,"quickCleanse":0,"quickFirstTurret":0,"quickSoloKills":0,"riftHeraldTakedowns":1,"saveAllyFromDeath":0,"scuttleCrabKills":0,"skillshotsDodged":16,"skillshotsHit":30,"snowballsHit":0,"soloBaronKills":0,"soloKills":2,"soloTurretsLategame":0,"stealthWardsPlaced":4,"survivedSingleDigitHpCount":0,"survivedThreeImmobilizesInFight":0,"takedownOnFirstTurret":0,"takedowns":10,"takedownsAfterGainingLevelAdvantage":0,"takedownsBeforeJungleMinionSpawn":1,"takedownsFirst25Minutes":10,"takedownsInAlcove":0,"takedownsInEnemyFountain":0,"teamBaronKills":0,"teamDamagePercentage":0.19354750172291094,"teamElderDragonKills":0,"teamRiftHeraldKills":0,"threeWardsOneSweeperCount":0,"tookLargeDamageSurvived":0,"turretPlatesTaken":1,"turretTakedowns":1,"turretsTakenWithRiftHerald":0,"twentyMinionsIn3SecondsCount":0,"unseenRecalls":0,"visionScoreAdvantageLaneOpponent":0.47451022267341614,"visionScorePerMinute":0.23529659141195933,"wardTakedowns":0,"wardTakedownsBefore20M":0,"wardsGuarded":0},"champExperience":11311,"champLevel":13,"championId":45,"championName":"Veigar","championTransform":0,"consumablesPurchased":2,"damageDealtToBuildings":1011,"damageDealtToObjectives":1315,"damageDealtToTurrets":1011,"damageSelfMitigated":10250,"deaths":7,"detectorWardsPlaced":0,"doubleKills":0,"dragonKills":0,"eligibleForProgression":true,"firstBloodAssist":false,"firstBloodKill":false,"firstTowerAssist":false,"firstTowerKill":false,"gameEndedInEarlySurrender":false,"gameEndedInSurrender":true,"goldEarned":9725,"goldSpent":9335,"individualPosition":"MIDDLE","inhibitorKills":0,"inhibitorTakedowns":0,"inhibitorsLost":2,"item0":6656,"item1":1052,"item2":3158,"item3":4629,"item4":3191,"item5":2420,"item6":3340,"itemsPurchased":17,"killingSprees":2,"kills":8,"lane":"MIDDLE","largestCriticalStrike":0,"largestKillingSpree":3,"largestMultiKill":1,"longestTimeSpentLiving":839,"magicDamageDealt":65790,"magicDamageDealtToChampions":11699,"magicDamageTaken":9556,"neutralMinionsKilled":0,"nexusKills":0,"nexusLost":0,"nexusTakedowns":0,"objectivesStolen":0,"objectivesStolenAssists":0,"participantId":8,"pentaKills":0,"perks":{"statPerks":{"defense":5002,"flex":5008,"offense":5007},"styles":[{"description":"primaryStyle","selections":[{"perk":8112,"var1":913,"var2":0,"var3":0},{"perk":8139,"var1":808,"var2":0,"var3":0},{"perk":8120,"var1":2,"var2":10,"var3":3},{"perk":8105,"var1":13,"var2":5,"var3":0}],"style":8100},{"description":"subStyle","selections":[{"perk":8226,"var1":250,"var2":208,"var3":0},{"perk":8210,"var1":10,"var2":0,"var3":0}],"style":8200}]},"physicalDamageDealt":6240,"physicalDamageDealtToChampions":748,"physicalDamageTaken":9917,"profileIcon":3592,"puuid":"2t15WNtfFE6dMrJ7wJ26PxHY6Z5pxa4kSyr94MBxw0LtuynxtIoaU16R3YIkB4G1x5ax81o3QywqwQ","quadraKills":0,"riotIdName":"","riotIdTagline":"","role":"SOLO","sightWardsBoughtInGame":0,"spell1Casts":78,"spell2Casts":59,"spell3Casts":17,"spell4Casts":11,"summoner1Casts":3,"summoner1Id":4,"summoner2Casts":3,"summoner2Id":21,"summonerId":"xs_3K_yazGIOeTUD3tUqHJsbc8_aADmP3cEUvjshz5gi4DtA","summonerLevel":34,"summonerName":"OzvuYT","teamEarlySurrendered":false,"teamId":200,"teamPosition":"MIDDLE","timeCCingOthers":13,"timePlayed":1496,"totalDamageDealt":75189,"totalDamageDealtToChampions":12602,"totalDamageShieldedOnTeammates":0,"totalDamageTaken":21144,"totalHeal":1921,"totalHealsOnTeammates":0,"totalMinionsKilled":106,"totalTimeCCDealt":50,"totalTimeSpentDead":267,"totalUnitsHealed":1,"tripleKills":0,"trueDamageDealt":3159,"trueDamageDealtToChampions":154,"trueDamageTaken":1669,"turretKills":1,"turretTakedowns":1,"turretsLost":10,"unrealKills":0,"visionScore":5,"visionWardsBoughtInGame":0,"wardsKilled":0,"wardsPlaced":4,"win":false},{"assists":10,"baronKills":0,"bountyLevel":2,"challenges":{"12AssistStreakCount":0,"abilityUses":102,"acesBefore15Minutes":0,"alliedJungleMonsterKills":0,"baronTakedowns":0,"blastConeOppositeOpponentCount":0,"bountyGold":300,"buffsStolen":0,"completeSupportQuestInTime":0,"controlWardsPlaced":0,"damagePerMinute":447.0353041177508,"damageTakenOnTeamPercentage":0.17464638573624222,"dancedWithRiftHerald":0,"deathsByEnemyChamps":8,"dodgeSkillShotsSmallWindow":37,"doubleAces":0,"dragonTakedowns":1,"earliestDragonTakedown":616.9563225897688,"earlyLaningPhaseGoldExpAdvantage":0.15828204154968262,"effectiveHealAndShielding":495,"elderDragonKillsWithOpposingSoul":0,"elderDragonMultikills":0,"enemyChampionImmobilizations":11,"enemyJungleMonsterKills":0,"epicMonsterKillsNearEnemyJungler":0,"epicMonsterKillsWithin30SecondsOfSpawn":0,"epicMonsterSteals":0,"epicMonsterStolenWithoutSmite":0,"flawlessAces":0,"fullTeamTakedown":2,"gameLength":1496.672637819821,"getTakedownsInAllLanesEarlyJungleAsLaner":0,"goldPerMinute":401.5317099087954,"hadAfkTeammate":0,"hadOpenNexus":0,"immobilizeAndKillWithAlly":8,"initialBuffCount":0,"initialCrabCount":0,"jungleCsBefore10Minutes":0,"junglerTakedownsNearDamagedEpicMonster":0,"kTurretsDestroyedBeforePlatesFall":0,"kda":1.875,"killAfterHiddenWithAlly":2,"killParticipation":0.375,"killedChampTookFullTeamDamageSurvived":0,"killsNearEnemyTurret":0,"killsOnOtherLanesEarlyJungleAsLaner":0,"killsOnRecentlyHealedByAramPack":0,"killsUnderOwnTurret":1,"killsWithHelpFromEpicMonster":0,"knockEnemyIntoTeamAndKill":0,"landSkillShotsEarlyGame":7,"laneMinionsFirst10Minutes":70,"laningPhaseGoldExpAdvantage":-0.1734575629234314,"legendaryCount":0,"lostAnInhibitor":0,"maxCsAdvantageOnLaneOpponent":13,"maxKillDeficit":0,"maxLevelLeadLaneOpponent":1,"moreEnemyJungleThanOpponent":-123.00000008940697,"multiKillOneSpell":0,"multiTurretRiftHeraldCount":0,"multikills":0,"multikillsAfterAggressiveFlash":0,"mythicItemUsed":6671,"outerTurretExecutesBefore10Minutes":0,"outnumberedKills":0,"outnumberedNexusKill":0,"perfectDragonSoulsTaken":0,"perfectGame":0,"pickKillWithAlly":13,"poroExplosions":0,"quickCleanse":0,"quickFirstTurret":0,"quickSoloKills":0,"riftHeraldTakedowns":1,"saveAllyFromDeath":0,"scuttleCrabKills":0,"skillshotsDodged":26,"skillshotsHit":43,"snowballsHit":0,"soloBaronKills":0,"soloKills":0,"soloTurretsLategame":0,"stealthWardsPlaced":4,"survivedSingleDigitHpCount":1,"survivedThreeImmobilizesInFight":0,"takedownOnFirstTurret":1,"takedowns":15,"takedownsAfterGainingLevelAdvantage":0,"takedownsBeforeJungleMinionSpawn":2,"takedownsFirst25Minutes":15,"takedownsInAlcove":1,"takedownsInEnemyFountain":0,"teamBaronKills":0,"teamDamagePercentage":0.17125949100824223,"teamElderDragonKills":0,"teamRiftHeraldKills":0,"threeWardsOneSweeperCount":0,"tookLargeDamageSurvived":0,"turretPlatesTaken":1,"turretTakedowns":1,"turretsTakenWithRiftHerald":0,"twentyMinionsIn3SecondsCount":0,"unseenRecalls":0,"visionScoreAdvantageLaneOpponent":0.18530356884002686,"visionScorePerMinute":0.22120408969055572,"wardTakedowns":1,"wardTakedownsBefore20M":0,"wardsGuarded":0},"champExperience":9686,"champLevel":12,"championId":202,"championName":"Jhin","championTransform":0,"consumablesPurchased":2,"damageDealtToBuildings":868,"damageDealtToObjectives":1734,"damageDealtToTurrets":868,"damageSelfMitigated":6381,"deaths":8,"detectorWardsPlaced":0,"doubleKills":0,"dragonKills":0,"eligibleForProgression":true,"firstBloodAssist":true,"firstBloodKill":false,"firstTowerAssist":false,"firstTowerKill":false,"gameEndedInEarlySurrender":false,"gameEndedInSurrender":true,"goldEarned":10016,"goldSpent":9600,"individualPosition":"BOTTOM","inhibitorKills":0,"inhibitorTakedowns":0,"inhibitorsLost":2,"item0":1055,"item1":6671,"item2":3009,"item3":6676,"item4":2015,"item5":3086,"item6":3340,"itemsPurchased":17,"killingSprees":2,"kills":5,"lane":"BOTTOM","largestCriticalStrike":922,"largestKillingSpree":3,"largestMultiKill":1,"longestTimeSpentLiving":744,"magicDamageDealt":2634,"magicDamageDealtToChampions":966,"magicDamageTaken":9049,"neutralMinionsKilled":0,"nexusKills":0,"nexusLost":0,"nexusTakedowns":0,"objectivesStolen":0,"objectivesStolenAssists":0,"participantId":9,"pentaKills":0,"perks":{"statPerks":{"defense":5002,"flex":5008,"offense":5005},"styles":[{"description":"primaryStyle","selections":[{"perk":8128,"var1":780,"var2":13,"var3":0},{"perk":8139,"var1":986,"var2":0,"var3":0},{"perk":8138,"var1":18,"var2":0,"var3":0},{"perk":8135,"var1":400,"var2":5,"var3":0}],"style":8100},{"description":"subStyle","selections":[{"perk":8234,"var1":8011,"var2":0,"var3":0},{"perk":8226,"var1":250,"var2":166,"var3":0}],"style":8200}]},"physicalDamageDealt":79626,"physicalDamageDealtToChampions":9990,"physicalDamageTaken":8518,"profileIcon":4990,"puuid":"n09AHR4pCB3LkDMJLWiVDh0eIFFcN98oOpVoJlW42RbJcmdltjOJzF4rA6NeMJ6UhvkWk4U1m19l0w","quadraKills":0,"riotIdName":"","riotIdTagline":"","role":"CARRY","sightWardsBoughtInGame":0,"spell1Casts":41,"spell2Casts":27,"spell3Casts":14,"spell4Casts":20,"summoner1Casts":3,"summoner1Id":4,"summoner2Casts":4,"summoner2Id":7,"summonerId":"RjKjwUd2wTibI_Ynew6dbwuEITC5g-G2KmSO4tODheAdI20","summonerLevel":177,"summonerName":"BaneOfHonor","teamEarlySurrendered":false,"teamId":200,"teamPosition":"BOTTOM","timeCCingOthers":18,"timePlayed":1496,"totalDamageDealt":84950,"totalDamageDealtToChampions":11151,"totalDamageShieldedOnTeammates":0,"totalDamageTaken":19287,"totalHeal":2126,"totalHealsOnTeammates":495,"totalMinionsKilled":136,"totalTimeCCDealt":87,"totalTimeSpentDead":228,"totalUnitsHealed":3,"tripleKills":0,"trueDamageDealt":2689,"trueDamageDealtToChampions":193,"trueDamageTaken":1719,"turretKills":0,"turretTakedowns":1,"turretsLost":10,"unrealKills":0,"visionScore":5,"visionWardsBoughtInGame":0,"wardsKilled":1,"wardsPlaced":4,"win":false},{"assists":10,"baronKills":0,"bountyLevel":0,"challenges":{"12AssistStreakCount":0,"abilityUses":125,"acesBefore15Minutes":0,"alliedJungleMonsterKills":0,"baronTakedowns":0,"blastConeOppositeOpponentCount":0,"bountyGold":450,"buffsStolen":0,"completeSupportQuestInTime":1,"controlWardsPlaced":0,"damagePerMinute":593.5480391149804,"damageTakenOnTeamPercentage":0.2048060688996729,"dancedWithRiftHerald":0,"deathsByEnemyChamps":8,"dodgeSkillShotsSmallWindow":37,"doubleAces":0,"dragonTakedowns":1,"earliestDragonTakedown":1252.3043345538704,"earlyLaningPhaseGoldExpAdvantage":0.07310640811920166,"effectiveHealAndShielding":0,"elderDragonKillsWithOpposingSoul":0,"elderDragonMultikills":0,"enemyChampionImmobilizations":26,"enemyJungleMonsterKills":0,"epicMonsterKillsNearEnemyJungler":0,"epicMonsterKillsWithin30SecondsOfSpawn":0,"epicMonsterSteals":0,"epicMonsterStolenWithoutSmite":0,"fasterSupportQuestCompletion":1,"flawlessAces":0,"fullTeamTakedown":2,"gameLength":1496.672637819821,"getTakedownsInAllLanesEarlyJungleAsLaner":0,"goldPerMinute":341.2424268469086,"hadAfkTeammate":0,"hadOpenNexus":0,"immobilizeAndKillWithAlly":9,"initialBuffCount":0,"initialCrabCount":0,"jungleCsBefore10Minutes":0,"junglerTakedownsNearDamagedEpicMonster":0,"kTurretsDestroyedBeforePlatesFall":0,"kda":1.75,"killAfterHiddenWithAlly":1,"killParticipation":0.35,"killedChampTookFullTeamDamageSurvived":0,"killsNearEnemyTurret":0,"killsOnOtherLanesEarlyJungleAsLaner":0,"killsOnRecentlyHealedByAramPack":0,"killsUnderOwnTurret":1,"killsWithHelpFromEpicMonster":0,"knockEnemyIntoTeamAndKill":9,"landSkillShotsEarlyGame":4,"laneMinionsFirst10Minutes":3,"laningPhaseGoldExpAdvantage":-0.031434595584869385,"legendaryCount":0,"lostAnInhibitor":0,"maxCsAdvantageOnLaneOpponent":7,"maxKillDeficit":0,"maxLevelLeadLaneOpponent":1,"moreEnemyJungleThanOpponent":-123.00000008940697,"multiKillOneSpell":1,"multiTurretRiftHeraldCount":0,"multikills":0,"multikillsAfterAggressiveFlash":0,"mythicItemUsed":6653,"outerTurretExecutesBefore10Minutes":0,"outnumberedKills":1,"outnumberedNexusKill":0,"perfectDragonSoulsTaken":0,"perfectGame":0,"pickKillWithAlly":11,"poroExplosions":0,"quickCleanse":0,"quickFirstTurret":0,"quickSoloKills":0,"riftHeraldTakedowns":0,"saveAllyFromDeath":0,"scuttleCrabKills":0,"skillshotsDodged":40,"skillshotsHit":38,"snowballsHit":0,"soloBaronKills":0,"soloKills":0,"soloTurretsLategame":0,"stealthWardsPlaced":12,"survivedSingleDigitHpCount":0,"survivedThreeImmobilizesInFight":0,"takedownOnFirstTurret":0,"takedowns":14,"takedownsAfterGainingLevelAdvantage":0,"takedownsBeforeJungleMinionSpawn":2,"takedownsFirst25Minutes":14,"takedownsInAlcove":0,"takedownsInEnemyFountain":0,"teamBaronKills":0,"teamDamagePercentage":0.22738860696558452,"teamElderDragonKills":0,"teamRiftHeraldKills":0,"threeWardsOneSweeperCount":0,"tookLargeDamageSurvived":0,"turretPlatesTaken":2,"turretTakedowns":0,"turretsTakenWithRiftHerald":0,"twentyMinionsIn3SecondsCount":0,"unseenRecalls":0,"visionScoreAdvantageLaneOpponent":0.7137964963912964,"visionScorePerMinute":0.9686162914361298,"wardTakedowns":1,"wardTakedownsBefore20M":1,"wardsGuarded":0},"champExperience":9863,"champLevel":12,"championId":50,"championName":"Swain","championTransform":0,"consumablesPurchased":2,"damageDealtToBuildings":1283,"damageDealtToObjectives":1750,"damageDealtToTurrets":1283,"damageSelfMitigated":7431,"deaths":8,"detectorWardsPlaced":0,"doubleKills":0,"dragonKills":0,"eligibleForProgression":true,"firstBloodAssist":true,"firstBloodKill":false,"firstTowerAssist":false,"firstTowerKill":false,"gameEndedInEarlySurrender":false,"gameEndedInSurrender":true,"goldEarned":8512,"goldSpent":7950,"individualPosition":"UTILITY","inhibitorKills":0,"inhibitorTakedowns":0,"inhibitorsLost":2,"item0":3157,"item1":3853,"item2":6653,"item3":3020,"item4":3916,"item5":0,"item6":3364,"itemsPurchased":15,"killingSprees":1,"kills":4,"lane":"BOTTOM","largestCriticalStrike":0,"largestKillingSpree":2,"largestMultiKill":1,"longestTimeSpentLiving":812,"magicDamageDealt":57639,"magicDamageDealtToChampions":12115,"magicDamageTaken":13630,"neutralMinionsKilled":0,"nexusKills":0,"nexusLost":0,"nexusTakedowns":0,"objectivesStolen":0,"objectivesStolenAssists":0,"participantId":10,"pentaKills":0,"perks":{"statPerks":{"defense":5001,"flex":5008,"offense":5008},"styles":[{"description":"primaryStyle","selections":[{"perk":8112,"var1":1207,"var2":0,"var3":0},{"perk":8126,"var1":339,"var2":0,"var3":0},{"perk":8138,"var1":30,"var2":0,"var3":0},{"perk":8106,"var1":5,"var2":0,"var3":0}],"style":8100},{"description":"subStyle","selections":[{"perk":8313,"var1":0,"var2":0,"var3":0},{"perk":8347,"var1":0,"var2":0,"var3":0}],"style":8300}]},"physicalDamageDealt":2709,"physicalDamageDealtToChampions":1231,"physicalDamageTaken":7448,"profileIcon":935,"puuid":"LtFdHX4-a5Jds973njAW3P6FSadqDKL3Jo3Jf0ZNI2r5E_euTaW7wL77ViGolVHOvicXbIFUO5XqPA","quadraKills":0,"riotIdName":"","riotIdTagline":"","role":"SUPPORT","sightWardsBoughtInGame":0,"spell1Casts":40,"spell2Casts":32,"spell3Casts":41,"spell4Casts":12,"summoner1Casts":7,"summoner1Id":14,"summoner2Casts":3,"summoner2Id":4,"summonerId":"vqCVVluD1rYgaM9QNLm3dm8i9LY0z--n6_G8uHbT3bp0H6Q","summonerLevel":249,"summonerName":"CyborgCthulhu11","teamEarlySurrendered":false,"teamId":200,"teamPosition":"UTILITY","timeCCingOthers":24,"timePlayed":1496,"totalDamageDealt":61807,"totalDamageDealtToChampions":14805,"totalDamageShieldedOnTeammates":0,"totalDamageTaken":22617,"totalHeal":3887,"totalHealsOnTeammates":0,"totalMinionsKilled":56,"totalTimeCCDealt":154,"totalTimeSpentDead":261,"totalUnitsHealed":1,"tripleKills":0,"trueDamageDealt":1459,"trueDamageDealtToChampions":1459,"trueDamageTaken":1539,"turretKills":0,"turretTakedowns":0,"turretsLost":10,"unrealKills":0,"visionScore":24,"visionWardsBoughtInGame":0,"wardsKilled":1,"wardsPlaced":12,"win":false}],"platformId":"NA1","queueId":440,"teams":[{"bans":[{"championId":53,"pickTurn":1},{"championId":41,"pickTurn":2},{"championId":107,"pickTurn":3},{"championId":51,"pickTurn":4},{"championId":74,"pickTurn":5}],"objectives":{"baron":{"first":true,"kills":1},"champion":{"first":false,"kills":40},"dragon":{"first":true,"kills":3},"inhibitor":{"first":true,"kills":2},"riftHerald":{"first":true,"kills":2},"tower":{"first":true,"kills":10}},"teamId":100,"win":true},{"bans":[{"championId":48,"pickTurn":6},{"championId":777,"pickTurn":7},{"championId":555,"pickTurn":8},{"championId":154,"pickTurn":9},{"championId":103,"pickTurn":10}],"objectives":{"baron":{"first":false,"kills":0},"champion":{"first":true,"kills":27},"dragon":{"first":false,"kills":0},"inhibitor":{"first":false,"kills":0},"riftHerald":{"first":false,"kills":0},"tower":{"first":false,"kills":1}},"teamId":200,"win":false}],"tournamentCode":""}}